Workbook

Sheet Priority Targets
A1: Tier | B1: Company | C1: Booth # | D1: Hall | E1: Type | F1: Angle | G1: Why / pitch hook / ask | H1: Public contact | I1: Suggested day | J1: Status | K1: Rep notes | L1: Source
A2: A | B2: Yamazen Inc. | C2: 338536 | D2: South L3 | E2: Importer + tooling division | F2: Distributor / bundle | G2: Brother SPEEDIO = BT30/BBT30 world. Yamazen sells tooling. Ask: who runs the Tooling Division, can HIPPSC be a value shrink-fit line or the holder package on Brother/Matsuura demos? | H2: Ask at booth for Tooling Division manager | I2: Tue | L2: yamazen.com/events/imts-2026
A3: A | B3: Methods Machine Tools | C3: 339033 | D3: South L3 | E3: Importer / dealer / automation | F3: Distributor / bundle | G3: Yasda (HSK-E/A63), RoboDrill (BT30), Nakamura. Multi-line dealer with automation division. Ask: tooling package on Yasda/RoboDrill installs; automation division interest in a shrink+preset station. | I3: Tue | L3: methodsmachine.com/event/imts-2026
A4: A | B4: Ellison Technologies (at DN Solutions booth) | C4: 338919 | D4: South L3 | E4: Machine tool dealer (CA/TX/Midwest/SE) | F4: Distributor / bundle | G4: Largest DN Solutions dealer. Booth reception Tue 9/15 4-7 pm, daily 4 pm happy hour. Ask: tooling packages on DVF 5-axis (HSK) installs. | H4: Tim Gaylor, Monty Smith (Ellison) | I4: Tue | L4: ellisontechnologies.com/imts2026
A5: A | B5: Productivity Inc. (at Haas/Makino/Matsuura/Hwacheon/Citizen booths) | C5: 338100 / 338519 / 338630 / 339148 / 339419 | D5: South L3 | E5: Dealer (MN/IA/NE/Dakotas) | F5: Distributor | G5: Hosts customers at builder booths 9-noon daily. Sells tooling & workholding. Approach after noon. | I5: Tue | L5: productivity.com/events/imts-2026
A6: A | B6: Morris Group (Okuma / Tsugami / Select booths) | C6: 338500 / 339410 / 339100 | D6: South L3 | E6: Dealer network (NE/SE/Midwest) | F6: Distributor | G6: Okuma + Tsugami + Hardinge network. Ask who handles tooling lines. | I6: Tue | L6: mtdcnc.com Morris IMTS 2026
A7: A | B7: Absolute Machine Tools (You Ji) | C7: 339476 | D7: South L3 | E7: Importer (Taiwan machines), Ohio dealer network | F7: Bundle / distributor | G7: You Ji VTL built for Capto; BT50. Importer model = open to tooling bundles. | I7: Tue | L7: absolutemachine.com/event/imts
A8: A | B8: Expand Machinery (Ganesh/Genturn/Genmill) | C8: 338045 | D8: South L3 | E8: Importer, California | F8: Bundle / distributor | G8: BT40 value segment, CA-based (near HIPPSC LA). Natural first bundle partner. | I8: Tue | L8: directory 00051908
A9: A | B9: MSC Industrial Supply | C9: 432228 | D9: West L3 (Tooling) | E9: National industrial distributor | F9: Distributor (long game) | G9: Carries Haimer/Techniks. Ask: process for onboarding a new toolholding line, category manager name, private-label program. | I9: Mon | L9: directory 00041998
A10: A | B10: Shars Tool Company | C10: 134506 | D10: East L3 | E10: Value tooling distributor (IL) | F10: Distributor | G10: Already sells import holders. Ask: interest in a branded shrink-fit line + $6.8K machine at their price tier. | I10: Thu | L10: directory 00005979
A11: A | B11: TOOL HOLDER SHOP INC. | C11: 432097 | D11: West L3 (Tooling) | E11: Pure toolholder reseller | F11: Distributor | G11: Directory says 'CNC machine tools tool holders distributor'. Ask: current sources, gaps (shrink fit? HSK?), private-label interest. | I11: Mon | L11: directory 1001613
A12: A | B12: Accutek | C12: 431591 | D12: West L3 (Tooling) | E12: Holder + hydraulic + presetting brand (import-style) | F12: OEM / private-label | G12: Accutek brands imported holders. Ask: sourcing shrink fit / HSK, second-source interest. | I12: Mon | L12: accutekusa.com
A13: A | B13: PAC Precision Tools USA | C13: 432061 | D13: West L3 (Tooling) | E13: CNC toolholders, collets | F13: OEM / private-label / distributor | G13: Small holder brand. Ask: do they source or make? Private-label shrink line. | I13: Mon | L13: directory 1001045
A14: A | B14: Delton International USA | C14: 431573 | D14: West L3 (Tooling) | E14: One-stop importer w/ US inventory (MI) | F14: Distributor / private-label | G14: Importer model with US stock. Ask: add shrink-fit + machine. | I14: Mon | L14: directory 1001059
A15: A | B15: Royal Products | C15: 431622 | D15: West L3 (Tooling) | E15: Accessory brand (NY) | F15: OEM / private-label | G15: Sells accessory lines under own brand. Ask: shrink fit under Royal label. | I15: Mon | L15: directory 00002342
A16: A | B16: Omega TMM | C16: 432220 | D16: West L3 (Tooling) | E16: US-made presetters; ShrinkSet shrink station | F16: OEM partner (holders for demos) | G16: Co-markets Techniks/Parlec holders at booth. They need holders; HIPPSC needs a US-made presetter to bundle. Ask: mutual referral, demo holders. | I16: Mon | L16: omegatmm.com/imts2026
... A21: A | B21: JM Performance Products | C21: 431961 | D21: West L3 (Tooling) | E21: High-torque retention knobs (OH) | F21: Co-sell partner | G21: Every CAT/BT holder needs a pull stud. Ask: bundle JMPP knobs with HIPPSC holders; share dealer list. | I21: Mon | L21: directory 00056008
A22: A | B22: Fastems | C22: 338966 | D22: South L3 | E22: FMS / pallet automation | F22: Automation integration | G22: FMS users centralize tool setup. Ask: presetter/shrink station in their tool-storage flow; MMS tool-data interface. | H22: Chris Hansen, Sales Mgr US/Canada West, chris.hansen@fastems.com | I22: Tue | L22: fastems.com/events/imts-2026
A23: A | B23: Xometry | C23: 338368 | D23: South L3 | E23: Job-shop network / marketplace | F23: Supplier program | G23: Access to thousands of partner shops. Ask: supplier-perks / tooling partner program. | I23: Tue | L23: directory 00071405
A24: A | B24: Jingdiao North America | C24: 339153 | D24: South L3 | E24: Chinese machine OEM (Mt. Prospect IL) | F24: Ally / bundle | G24: Chinese OEM that built a US presence (HSK-E32/A63 machines). Ask: how they did it; holders on their demo machines. | I24: Tue | L24: us.jingdiao.com
A25: A | B25: ZCC - USA | C25: 431938 | D25: West L3 (Tooling) | E25: Chinese carbide brand, Ann Arbor MI | F25: Ally / lessons | G25: Entered US via 'select distributors' only. Ask: which distributors, how long, what worked. | I25: Mon | L25: zccusa.com
A26: A | B26: Euro-Tech Corporation | C26: 432272 | D26: West L3 (Tooling) | E26: Distributor of German tooling/workholding (WI) | F26: Distributor | G26: Imports German lines. Ask if they'd add a value shrink-fit line. | I26: Mon | L26: directory 00003320
A27: A | B27: T. Friedl Enterprises | C27: 432258 | D27: West L3 (Tooling) | E27: Importer/distributor (HAM drills, DTS) | F27: Distributor | G27: Importer model. Ask: shrink fit gap. | I27: Mon | L27: directory
A28: A | B28: U S Shop Tools / ABS Import Tools | C28: 432122 / 432083 | D28: West L3 (Tooling) | E28: National tooling distributors (import) | F28: Distributor | G28: Import channels. Ask: branded shrink fit + machine. | I28: Mon | L28: directory
A29: B | B29: Mazak | C29: 338300 | D29: South L3 | E29: OEM (largest live-cut booth) | F29: Co-demo / bundle | G29: CAT40 BIG-Plus, HSK-A63 VARIAXIS, Capto INTEGREX. Ask: tooling partner program for demo machines; MPP/Palletech cells need presetting. | H29: Dan Janka, President | I29: Tue | L29: mazak.com IMTS 2026
A30: B | B30: Okuma America | C30: 338500 | D30: South L3 | E30: OEM; 'Partners in Technology' program | F30: Co-demo / bundle | G30: Formal partner program for tooling vendors. Ask: how to join Partners in Technology; OFA automation. | H30: Simon Schneider (OFA), Wade Anderson (VP Eng), Tim Thiessen (VP Sales) | I30: Tue | L30: prnewswire Okuma IMTS 2026
A31: B | B31: Makino | C31: 338519 | D31: South L3 | E31: OEM (HSK heavy: a-series, DA500, V-series) | F31: Co-demo / bundle | G31: Aerospace/die-mold = shrink fit standard. Ask: tooling on demo cells. | I31: Tue | L31: makino.com/en-us/promotions/imts-2026
A32: B | B32: Hurco / Takumi / Milltronics | C32: 338319 | D32: South L3 | E32: OEM group | F32: Co-demo / bundle | G32: Takumi U800 = native HSK-A63 20k rpm 5-axis; BM500U 60/96 ATC. Ask: HIPPSC holders on Takumi demo. | I32: Tue | L32: americanmachinist Takumi IMTS 2026
A33: B | B33: DN Solutions America | C33: 338919 | D33: South L3 | E33: OEM (Doosan) | F33: Co-demo / bundle | G33: BT40/CAT40 BIG-Plus, Capto C6, HSK on DVF. Reception Tue 4-7. | I33: Tue | L33: ellisontechnologies.com/imts2026
A34: B | B34: Kitamura Machinery of USA | C34: 338520 | D34: South L3 | E34: OEM (82 distributors) | F34: Bundle | G34: BBT40/BBT50, HSK options. Ask for distributor list intro. | I34: Tue | L34: directory 00001900
A35: B | B35: Matsuura Machinery USA | C35: 338630 | D35: South L3 | E35: OEM (multi-pallet lights-out) | F35: Bundle | G35: BT40/HSK-A63; lights-out = presetting buyer. | I35: Tue | L35: directory 00062954
A36: B | B36: Hermle USA | C36: 339121 | D36: South L3 | E36: OEM (pure HSK-A63/A100) | F36: Co-demo | G36: ZM tool magazines drive tool assembly demand. | H36: info@hermleusa.net | I36: Tue | L36: hermleusa.net IMTS 2026
A37: B | B37: DATRON USA | C37: 338248 | D37: South L3 | E37: OEM (HSK-E25/E32/E40) | F37: Bundle | G37: Small shrink-fit sweet spot. | I37: Tue | L37: directory 00006754
A38: B | B38: Kern Precision | C38: 338719 | D38: South L3 | E38: OEM (HSK-E40/A63 micro) | F38: Bundle | G38: Shrink fit standard on Kern. | I38: Tue | L38: directory 00053924
A39: B | B39: Chiron America | C39: 339265 | D39: South L3 | E39: OEM (HSK-A63) | F39: Bundle | G39: Automotive/medical turnkey. | I39: Tue | L39: directory 00001648
A40: B | B40: MC Machinery Systems (Mitsubishi EDM / Roku-Roku) | C40: 338129 | D40: South L3 | E40: Importer | F40: Bundle | G40: Roku-Roku HSK-E32/E40 graphite/hard milling. | H40: Alan Hallmann, NA Sales Mgr EDM & Milling | I40: Tue | L40: mcmachinery.com/news/imts-2026-chicago
A41: B | B41: JTEKT (Toyoda) + Mitsui Seiki | C41: 338700 | D41: South L3 | E41: OEM | F41: Bundle | G41: CAT40/50 BIG-Plus, HSK; Mitsui HSK-E25 50k rpm. | I41: Tue | L41: directory 00000259
A42: B | B42: INDEX Corporation | C42: 339119 | D42: South L3 | E42: OEM | F42: Co-demo precedent | G42: Shows HORN tooling partners in booth = precedent for HIPPSC. | H42: Michael Huggett, President & CEO | I42: Tue | L42: directory 00001674
A43: B | B43: Heller Machine Tools | C43: 338930 | D43: South L3 | E43: OEM (HSK-A63/A100) | F43: Bundle | G43: Ellison co-staffs. | I43: Tue | L43: directory 00006284
A44: B | B44: SMEC America | C44: 338948 | D44: South L3 | E44: OEM (Korea, value) | F44: Bundle | G44: Capto C6 + BT40 value segment. | I44: Tue | L44: directory 00080605
A45: B | B45: Hwacheon Machinery America | C45: 339148 | D45: South L3 | E45: OEM (Korea) | F45: Bundle | G45: BT40/BT50 job shops; Productivity dealer. | I45: Tue | L45: directory 00001990
A46: B | B46: Haas Automation / Haas Tooling | C46: 338100 / 432212 | D46: South L3 | E46: OEM + own tooling line | F46: Competitor-channel | G46: Haas sells own shrink-fit holders + machine. Study Haas Tooling pricing at 432212. HFO network is the real target. | I46: Mon | L46: mtdcnc.com Haas IMTS
A47: B | B47: TRAK Machine Tools | C47: 338032 | D47: South L3 | E47: OEM (CAT40 job shops) | F47: Bundle | G47: Direct sales CA/TX/Midwest. | I47: Tue | L47: directory 00002603
A48: B | B48: Kent USA | C48: 339444 | D48: South L3 | E48: OEM/importer (entry) | F48: Bundle | G48: CAT40 entry segment. | I48: Tue | L48: directory 00001133
A49: B | B49: Phillips Corporation (Haas Factory Outlet) | C49: 338272 | D49: South L3 | E49: HFO / dealer | F49: Distributor | G49: Only HFO with own booth. Ask about tooling add-ons on Haas installs. | I49: Tue | L49: directory
A50: B | B50: Marubeni Citizen-Cincom | C50: 339419 | D50: South L3 | E50: Importer (Swiss) | F50: Low fit | G50: ER world; presetter angle only. | I50: Tue | L50: directory 00048943
A51: C | B51: HAIMER USA | C51: 431510 | D51: West L3 (Tooling) | E51: Primary competitor (Villa Park IL) | F51: Recon | G51: Shrink fit ecosystem + Automation Cube One. Collect: price sheet, lead times, Power Clamp pricing, automation cell video. Do not pitch. | H51: Brendt Holden, President & CEO | I51: Mon | L51: directory 00049702
A52: C | B52: BIG DAISHOWA (Speroni) | C52: 431610 | D52: West L3 (Tooling) | E52: Competitor (Hoffman Estates IL) | F52: Recon | G52: BIG-Plus dual contact; Speroni presetters; tool-assembly automation. | H52: Jack Burley, President/COO; Michael Herman, VP Sales | I52: Mon | L52: bigdaishowa.com
A53: C | B53: ZOLLER Inc. | C53: 432018 | D53: West L3 (Tooling) | E53: Competitor (Ann Arbor MI) | F53: Recon + integration | G53: powerShrink, roboBox, micBox debut, TMS. Toolroom of the Year award Thu 9/17 3:30 pm at booth (toolroom crowd). | H53: Alexander Zoller, President | I53: Mon/Thu | L53: newequipment.com Zoller IMTS 2026
A54: C | B54: SCHUNK | C54: 432010 / 236700 | D54: West L3 (Tooling) | E54: Competitor (hydraulic/polygonal) | F54: Recon | G54: TENDO, TRIBOS, CELSIO shrink. | H54: Milton Guerry, President | I54: Mon | L54: directory 00003668
A55: C | B55: Kennametal | C55: 431800 | D55: West L3 (Tooling) | E55: Competitor + co-demo model | F55: Recon | G55: Live 5-axis 'Next Level Shop' with OEM machines = the co-demo model to copy. | H55: Dave Bersaglini, VP & President Metal Cutting | I55: Mon | L55: prnewswire Kennametal IMTS 2026
A56: C | B56: REGO-FIX Tool Corp. | C56: 431822 | D56: West L3 (Tooling) | E56: Competitor (powRgrip vs shrink) | F56: Recon | G56: Press-fit alternative pitch; learn their anti-shrink talking points. | I56: Mon | L56: regousa.com
A57: C | B57: MST Corporation | C57: 431576 | D57: West L3 (Tooling) | E57: Competitor (premium slim shrink fit, Japan) | F57: Recon | G57: Slimline shrink fit; sold via Yamazen. | I57: Mon | L57: directory 00035487
A58: C | B58: Sandvik Coromant | C58: 338348 | D58: South L3 | E58: Competitor (Capto) | F58: Recon | G58: CoroPlus tool ID/management benchmark. | H58: Veronica Messersmith, President Americas | I58: Tue | L58: directory 00044967
A59: C | B59: CERATIZIT USA | C59: 431900 | D59: West L3 (Tooling) | E59: Competitor (secondary) | F59: Recon | G59: Holders + carbide. | I59: Mon | L59: directory 00043858
A60: C | B60: YG-1 Tool Co. | C60: 431400 | D60: West L3 (Tooling) | E60: Korean brand, US HQ Vernon Hills IL | F60: Recon / lessons | G60: Case study: stock + fill rate + 'Best Value'. Ask how they built distribution. | I60: Mon | L60: directory 00002104
A61: C | B61: Bright-Tools (Shandong Jinjie) | C61: 431370 | D61: West L3 (Tooling) | E61: Direct Chinese competitor | F61: Recon / ally | G61: Same aisle. Compare pricing; explore non-compete cooperation on US logistics. | H61: sales@bright-tools.com | I61: Mon | L61: bright-tools.com
A62: C | B62: Shandong Ounuowei | C62: 431264 | D62: West L3 (Tooling) | E62: Direct Chinese competitor | F62: Recon | G62: Shrink fit chucks, PSC/HSK. | I62: Mon | L62: directory 1001568
A63: C | B63: Evermore Machine Co. (Taiwan) | C63: 431756 | D63: West L3 (Tooling) | E63: Taiwanese OEM supplier to big brands | F63: Recon / benchmark | G63: OEM benchmark; Taiwan tariff 15% vs China ~41%. | I63: Mon | L63: directory 1001533
A64: C | B64: Parfaite Tool (Taiwan) | C64: 431771 | D64: West L3 (Tooling) | E64: Taiwanese competitor | F64: Recon | G64: Spindles + holders. | I64: Mon | L64: directory 1003930
A65: C | B65: Marposs / Renishaw / Blum | C65: 134324 / 134314 / 134710 | D65: East L3 | E65: In-machine tool setting | F65: Recon | G65: Alternative to offline presetting; learn objections. | I65: Thu | L65: directory
A66: C | B66: CMTBA (China Machine Tool & Tool Builders' Assoc.) | C66: 432580 | D66: West L3 (Tooling) | E66: Association | F66: Ally / intel | G66: International Associations row. Get list of Chinese exhibitors, joint events. | I66: Mon | L66: directory
A67: C | B67: Haas Tooling | C67: 432212 | D67: West L3 (Tooling) | E67: Competitor channel | F67: Recon | G67: Haas own-brand shrink fit pricing. | I67: Mon | L67: directory
A68: D | B68: Universal Robots (Teradyne) | C68: 236744 | D68: North L3 | E68: Cobots; UR+ partner ecosystem | F68: Integration | G68: Cobot for tool assembly cell. Ask about UR+ partner path. | I68: Wed | L68: directory 00072874
A69: D | B69: EROWA Technology | C69: 339072 | D69: South L3 | E69: Pallet/robot cells | F69: Integration | G69: Also does ITS presetting. | I69: Tue | L69: directory 00001620
A70: D | B70: Halter CNC Robotics | C70: 339288 | D70: South L3 | E70: Machine tending | F70: Integration | G70: Ellison/Hartwig partner. | I70: Tue | L70: directory 00078909
A71: D | B71: RoboJob | C71: 338982 | D71: South L3 | E71: CNC tending (100+ brands) | F71: Integration | I71: Tue | L71: directory 00089084
A72: D | B72: Vention | C72: 236860 | D72: North L3 | E72: Modular automation platform | F72: Integration | G72: Fast cobot cell for tool-assembly demo. | I72: Wed | L72: directory 00080239
A73: D | B73: Lang Technik USA | C73: 236637 | D73: North L3 | E73: Zero-point, RoboTrex | F73: Integration | I73: Wed | L73: directory 00059754
A74: D | B74: Flexxbotics | C74: 236044 | D74: North L3 | E74: Robot-CNC connectivity software | F74: Integration | G74: Tool-data layer. | I74: Wed | L74: directory 1004922
A75: D | B75: VersaBuilt Robotics | C75: 236300 | D75: North L3 | E75: Turnkey CNC cells | F75: Integration | I75: Wed | L75: directory 00066460
A76: D | B76: Formic Technologies | C76: 236329 | D76: North L3 | E76: Robots-as-a-service | F76: Integration | G76: Lights-out shops. | I76: Wed | L76: directory 00091015
A77: D | B77: KUKA Robotics | C77: 236807 | D77: North L3 | E77: Robots (tending w/ Matsuura, SYIL, EMAG) | F77: Integration | I77: Wed | L77: directory
A78: D | B78: Mitsubishi Electric Automation | C78: 338136 | D78: South L3 | E78: LoadMate machine tending | F78: Integration | H78: David Simak, Product Manager | I78: Tue | L78: directory
A79: D | B79: TDM Systems (Sandvik) | C79: 133125 | D79: East L3 | E79: Tool data / crib software | F79: Software partner | G79: Presetter-to-crib data. | I79: Thu | L79: directory 00047637
A80: D | B80: WinTool USA | C80: 133368 | D80: East L3 | E80: Tool management software | F80: Software partner | I80: Thu | L80: directory 00053651
A81: D | B81: CribMaster / Vidmar / LISTA | C81: 431485 | D81: West L3 (Tooling) | E81: Tool vending & storage | F81: Adjacent | G81: Tool-crib automation tie-in. | I81: Mon | L81: directory 00032666
A82: D | B82: Huayan Robotics (China) | C82: 236746 | D82: North L3 | E82: Chinese cobot first-timer | F82: Ally | G82: Fellow Chinese first-timer; share notes. | I82: Wed | L82: prnewswire Huayan IMTS 2026
A83: M | B83: IMTS Machinists' Hub (Practical Machinist) | C83: 432638 | D83: West L3 (Tooling) | E83: Media / daily happy hour | F83: Exposure | G83: Live talks, daily meetups, happy hours in YOUR hall. Ask host for a guest slot. | I83: Daily | L83: directory 1003995
A84: M | B84: IMTS Shops Zone (Gardner / Modern Machine Shop) | C84: 432634 | D84: West L3 (Tooling) | E84: Media / job-shop gathering | F84: Exposure | G84: Manufacturing Connected free founding-member signup; MMS editors here. | H84: Bill Caldwell (Gardner ads) billc@gardnerweb.com | I84: Daily | L84: additivemanufacturing.media
A85: M | B85: Cutting Tool Engineering booth | C85: 432313 | D85: West L3 (Tooling) | E85: Trade press (tooling) | F85: Exposure | G85: CTE writes 40+ booth briefs for Tooling hall. Pitch 'new US branch' story. | I85: Mon | L85: ctemag.com
A86: M | B86: IMTS Community Park (G28) | C86: 432200 | D86: West L3 (Tooling) | E86: Networking | F86: Exposure | G86: Cornhole, expert conversations. | I86: Daily | L86: directory 1004907
A87: M | B87: Manufacturing Showcase (GIE Media) | C87: 432636 | D87: West L3 (Tooling) | E87: Aero/defense crowd magnet | F87: Exposure | G87: Kratos drones; defense buyers. | I87: Mon | L87: directory 00046868
A88: M | B88: IMTS+ Technology Hubs | C88: 134476 / 338164 | D88: East L3 | E88: Stage | F88: Exposure | G88: Ask if non-exhibitor lightning slots exist. | I88: Tue/Thu | L88: directory
A89: M | B89: Media Center (press only) | C89: N426, North L4 | D89: North L4 | E89: Press | F89: Exposure | G89: Email Media@IMTS.com before show; do not walk in. | H89: Bonnie Gurney bgurney@AMTonline.org | I89: Pre-show | L89: imts.com/media
A91: Legend
A92: A | B92: Partnership candidates: distributors, importers, OEM/private-label, presetter makers, allies
A93: B | B93: Machine tool OEMs / importers: co-demo & tooling-bundle asks
A94: C | B94: Competitor recon: collect pricing, lead times, automation demos; do not pitch
A95: D | B95: Automation integrators / software: tool-setup automation fit
A96: M | B96: Media, hubs, associations: exposure
A98: Status column J has a dropdown (Not yet / Visited / Hot / Follow-up sent / Dead). Rep notes column K is free text. Booths verified against directory.imts.com on 2026-09-12; hall from booth prefix (1=East, 2=North, 3=South, 4=West).

Sheet Tier Summary
A1: Tier | B1: Targets | C1: Visited | D1: Hot | E1: Follow-up sent
A2: A | B2: =COUNTIF('Priority Targets'!$A$2:$A$89,A2) -> 27 | C2: =COUNTIFS('Priority Targets'!$A$2:$A$89,A2,'Priority Targets'!$J$2:$J$89,"Visited") -> 0 | D2: =COUNTIFS('Priority Targets'!$A$2:$A$89,A2,'Priority Targets'!$J$2:$J$89,"Hot") -> 0 | E2: =COUNTIFS('Priority Targets'!$A$2:$A$89,A2,'Priority Targets'!$J$2:$J$89,"Follow-up sent") -> 0
A3: B | B3: =COUNTIF('Priority Targets'!$A$2:$A$89,A3) -> 22 | C3: =COUNTIFS('Priority Targets'!$A$2:$A$89,A3,'Priority Targets'!$J$2:$J$89,"Visited") -> 0 | D3: =COUNTIFS('Priority Targets'!$A$2:$A$89,A3,'Priority Targets'!$J$2:$J$89,"Hot") -> 0 | E3: =COUNTIFS('Priority Targets'!$A$2:$A$89,A3,'Priority Targets'!$J$2:$J$89,"Follow-up sent") -> 0
A4: C | B4: =COUNTIF('Priority Targets'!$A$2:$A$89,A4) -> 17 | C4: =COUNTIFS('Priority Targets'!$A$2:$A$89,A4,'Priority Targets'!$J$2:$J$89,"Visited") -> 0 | D4: =COUNTIFS('Priority Targets'!$A$2:$A$89,A4,'Priority Targets'!$J$2:$J$89,"Hot") -> 0 | E4: =COUNTIFS('Priority Targets'!$A$2:$A$89,A4,'Priority Targets'!$J$2:$J$89,"Follow-up sent") -> 0
A5: D | B5: =COUNTIF('Priority Targets'!$A$2:$A$89,A5) -> 15 | C5: =COUNTIFS('Priority Targets'!$A$2:$A$89,A5,'Priority Targets'!$J$2:$J$89,"Visited") -> 0 | D5: =COUNTIFS('Priority Targets'!$A$2:$A$89,A5,'Priority Targets'!$J$2:$J$89,"Hot") -> 0 | E5: =COUNTIFS('Priority Targets'!$A$2:$A$89,A5,'Priority Targets'!$J$2:$J$89,"Follow-up sent") -> 0
A6: M | B6: =COUNTIF('Priority Targets'!$A$2:$A$89,A6) -> 7 | C6: =COUNTIFS('Priority Targets'!$A$2:$A$89,A6,'Priority Targets'!$J$2:$J$89,"Visited") -> 0 | D6: =COUNTIFS('Priority Targets'!$A$2:$A$89,A6,'Priority Targets'!$J$2:$J$89,"Hot") -> 0 | E6: =COUNTIFS('Priority Targets'!$A$2:$A$89,A6,'Priority Targets'!$J$2:$J$89,"Follow-up sent") -> 0
A7: Total | B7: =SUM(B2:B6) -> 88 | C7: =SUM(C2:C6) -> 0 | D7: =SUM(D2:D6) -> 0 | E7: =SUM(E2:E6) -> 0
A9: Counts update from the Status column on Priority Targets.

Sheet Events & Receptions
A1: Day | B1: Time (CT) | C1: Event | D1: Location | E1: Cost | F1: Why go / note
A2: Sun 9/13 | B2: all day | C2: DMG MORI Chicago Innovation Days (runs 9/13-9/18) | D2: DMG MORI Solutions Center, Hoffman Estates | E2: Free (register) | F2: Optional; off-site OEM open house
A3: Mon 9/14 | B3: 9:00-17:00 | C3: West Bldg (Tooling) open; South/North 10:00-18:00 | D3: McCormick Place | E3: Badge | F3: First hour + last 30 min = quiet booths
A4: Mon-Fri | B4: ~16:30 | C4: Machinists' Hub happy hour (verify time on site) | D4: West 432638 | E4: Free | F4: Daily; ask host for guest slot
A5: Tue 9/15 | B5: 8:30-13:00 | C5: Dia de America Latina conf | D5: West W194-B | E5: $150 | F5: Skip unless LATAM interest
A6: Tue 9/15 | B6: 13:00-16:30 | C6: Job Shops Workshop + reception 16:30-18:00 W196 Foyer | D6: West W196-A | E6: $345 | F6: Job shop owners; pricey
A7: Tue 9/15 | B7: 16:00-19:00 | C7: DN Solutions / Ellison booth reception | D7: South 338919 | E7: Free | F7: Dealers + DN customers
A8: Tue 9/15 | B8: 17:00-18:00 | C8: Haas After-Hours | D8: South 338100 | E8: Free | F8: Haas customers/HFO staff
A9: Tue 9/15 | B9: 17:00-19:30 | C9: Noche Latina Recepcion | D9: West W196-BC | E9: $40 | F9: Cheapest paid networking room
A10: Tue 9/15 | B10: 17:00-18:30 | C10: IMTS Investor Summit VIP reception | D10: Hyatt Regency McCormick, Prairie Room | E10: $595 (summit) | F10: Skip
A11: Tue 9/15 | B11: 18:00-20:00 | C11: German Night Reception (GACC Midwest / Wintrust) | D11: South Bldg Vista Room Lobby | E11: $85 | F11: ~350 decision-makers; Haimer/Zoller/German-owned shops; BEST buy
A12: Wed 9/16 | B12: 07:00 | C12: Miles for Manufacturing 5K / 1-mile | D12: DuSable Harbor, 111 N Lake Shore Dr | E12: $40/$30 | F12: AMT staff + exhibitor execs
... A19: Sat 9/19 | B19: 9:00-13:00 (Summit) | C19: Last day; student-heavy; teardown | D19: All halls | E19: Badge | F19: Optional; demo units get sold/given away

Sheet Not Exhibiting (off-show)
A1: Company | B1: Location | C1: Why they matter | D1: Public contact | E1: Note
A2: Techniks Tool Group (incl. Parlec) | B2: Indianapolis IN | C2: Top OEM/private-label target; Taiwan-sourced US brand; ShrinkFIT line | D2: Dean Glover, President & CEO; Mike Eneix, VP Sales; Greg Webb, EVP Bus Dev | E2: Not in 2026 directory; shown at Omega TMM 432220 partner display. Staff may walk floor - watch badges.
A3: Lyndex-Nikken | B3: Mundelein IL | C3: Holders, Elbo Controlli presetters, shrink machines | D3: Osmar Takeuchi, President | E3: 2026 listing withdrawn. Chicago-area: offer to visit after show.
A4: Maritool | B4: Aurora IL | C4: US-made value shrink fit, $196.30 CAT40 1/2" - your price benchmark | E4: Not exhibiting; Chicago suburb. Visit or call after show.
A5: Command Tooling Systems | B5: Ramsey MN | C5: Holders, shrink | E5: Not exhibiting.
A6: Briney Tooling Systems | B6: Bad Axe MI | C6: Holders, shrink | E6: Not exhibiting.
A7: Hoffmann Group USA (GARANT) | B7: Knoxville TN | C7: White-label catalog brand (GARANT shrink holders) | E7: Private-label benchmark; approach off-show.
A8: DMG MORI | B8: Hoffman Estates IL | C8: Chicago Innovation Days Sept 13-18 at their Solutions Center (~35 mi NW of McCormick) | E8: Not at IMTS. Optional half-day visit; HSK/Capto machines, own presetters.
A9: Fastenal / Grainger / DGI Supply / Production Tool Supply / Travers | B9: various | C9: Distributors | E9: Not exhibiting; off-show outreach.
A10: Hartwig / Gosiger / Hillary / Arthur Machinery / Machinery Systems / Trident / Selway / Hales / Toolmex / Arizona CNC | B10: various | C10: Machine tool dealers | E10: No own booth; staff OEM booths (Okuma, Mazak, Makino, DN). Watch badges at OEM booths.

Sheet Toolholding Category (all)
A1: Company | B1: Booth # | C1: Hall | D1: Directory categories | E1: Description (directory) | F1: Directory URL
A2: 5th Axis Inc. | B2: 431452 | C2: West L3 | D2: Hydraulic Toolholders | E2: Regarded as one of the world’s most innovative manufacturers, 5th Axis offers a full range of workholding solutions. 5th Axis’s product line includes vises, fixtures, dovetail cutters and the ever-popular Rock Lock quick-change system that provides machine shops the edge they need to stay efficient, competitive, and profitable. | F2: https://directory.imts.com/8_0/exhibitor/exhibitor-details.cfm?exhid=00059859
A3: AB Tools Inc. | B3: 432264 | C3: West L3 | D3: Hydraulic Toolholders, Tool Holders & Adapters | E3: USA made since 1977, Special Cutting Tools, Home of the Shear Hog® & Accu-hold, Indexable Dovetails, O-Ring grooving tools, Keyseat cutters, Firearms tooling in stock & Specials to your specs in 5-6 workdays. | F3: https://directory.imts.com/8_0/exhibitor/exhibitor-details.cfm?exhid=00046545
A4: ABS Import Tools Inc. | B4: 134618,432083 | C4: East L3, West L3 | D4: Hydraulic Toolholders, Tool Holders & Adapters | E4: Henry Xu founded ABS Import Tools in 1992 to provide high-quality tools and industrial supplies at competitive prices. With a 98% fill rate, the company ensures swift shipping and reliable service. ABS Import Tools now offers products from Dasqua and Harlingen across the USA and the Americas. | F4: https://directory.imts.com/8_0/exhibitor/exhibitor-details.cfm?exhid=00002966
A5: Accutek | B5: 431591 | C5: West L3 | D5: Collet Chucks, Hydraulic Toolholders, Tool Holders & Adapters, Tool Presetting Equipment | E5: Accutek® is a premier manufacturer of tool holding and work holding solutions. Given the constant evolution of tooling and machining technology plus the ever-increasing needs of our customers for greater accuracy and efficiency, Accutek is committed to developing innovative products and expanding our product offering to meet our customers’ needs. | F5: https://directory.imts.com/8_0/exhibitor/exhibitor-details.cfm?exhid=00075173
A6: Achieve Technologies Inc | B6: 432256 | C6: West L3 | D6: Collet Chucks, Hydraulic Toolholders, Tool Holders & Adapters | E6: Achieve Technologies delivers advanced CNC turrets, live tooling, CAPTO/PSC systems, and our patented Machine Tool Robot for high‑precision robotic milling and mill‑turn lathes. Our engineering experts provide turret and application engineering, rebuilds, and service, supplying premium tooling and automation solutions that maximize uptime, accuracy, and productivity across North America. | F6: https://directory.imts.com/8_0/exhibitor/exhibitor-details.cfm?exhid=00070259
A7: Advanced Machine & Engineering | B7: 339133 | C7: South L3 | D7: Hydraulic Toolholders, Tool Holders & Adapters | E7: About Advanced Machine & Engineering (AME) Founded in 1966, Advanced Machine & Engineering (AME) is a leading manufacturer and distributor of precision machine tool components and metal-cutting solutions — including AMROK CNC tombstones, fixture plates, and modular workholding systems; OTT-JAKOB tool clamping systems; machine design components; and custom machining and automation. Now unified unde | F7: https://directory.imts.com/8_0/exhibitor/exhibitor-details.cfm?exhid=00001606
A8: Allied Machine & Engineering | B8: 431436 | C8: West L3 | D8: Hydraulic Toolholders, Tool Holders & Adapters | E8: Allied Machine & Engineering Corp is a leading manufacturer of holemaking and finishing tooling systems. Allied devotes its advanced engineering and manufacturing capabilities to create the widest selection of value-added tooling available to metal-cutting industries around the world. Our tooling solutions deliver the lowest cost-per-hole in a wide range of drilling , boring , reaming , threading | F8: https://directory.imts.com/8_0/exhibitor/exhibitor-details.cfm?exhid=00001382
A9: Aloris Tool Technology Co., Inc. | B9: 431972 | C9: West L3 | D9: Hydraulic Toolholders, Tool Holders & Adapters | F9: https://directory.imts.com/8_0/exhibitor/exhibitor-details.cfm?exhid=00001383
A10: ARNO-Werkzeuge USA LLC | B10: 431585 | C10: West L3 | D10: Hydraulic Toolholders, Tool Holders & Adapters | E10: Outstanding Solutions for Precision Turned Components. ARNO USA brings innovative turning, grooving, parting, and hole making solutions to the high production, bar-fed turned components market as well as those who are running traditional turning centers. | F10: https://directory.imts.com/8_0/exhibitor/exhibitor-details.cfm?exhid=00001524
A11: ATI Industrial Automation | B11: 236144 | C11: North L3 | D11: Hydraulic Toolholders | E11: ATI INDUSTRIAL AUTOMATION , a Novanta Company, is the world-leading engineering-based developer of robotic accessories and robot arm tooling, including Robotic Tool Changers, Force/Torque Sensors, Material Removal Tools, and more. Their robot end-effector products are found in thousands of successful applications around the world. Since 1989, their team of mechanical, electrical, and software engi | F11: https://directory.imts.com/8_0/exhibitor/exhibitor-details.cfm?exhid=00001575
A12: Autodesk Inc. | B12: 133310 | C12: East L3 | D12: Other | E12: Autodesk is changing how the world is designed and made. Our technology spans countless industries, empowering innovators everywhere to solve challenges big and small. From greener buildings to smarter products to more mesmerizing blockbusters, Autodesk software helps our customers to design and make a better world for all. | F12: https://directory.imts.com/8_0/exhibitor/exhibitor-details.cfm?exhid=00005408
A13: Axtra3D | B13: 338374 | C13: South L3 | D13: Hydraulic Toolholders | E13: Axtra3D's Hi-Speed SLA merges laser and DLP imaging in one process, eliminating tradeoffs between throughput, fidelity, and size. Fully validated, production-proven workflows for injection molding ceramic mold inserts, low-pressure molds, micro molds, electrical connectors, elastomers, ESD, flame-retardant parts, and low-volume production deliver production-ready performance. | F13: https://directory.imts.com/8_0/exhibitor/exhibitor-details.cfm?exhid=1002148
A14: AXYZ Routers and WARDJET Waterjets | B14: 134764 | C14: East L3 | D14: Hydraulic Toolholders, Tool Holders & Adapters | E14: AXYZ Routers, a leader in CNC technology for over 30 years, offers advanced precision routing solutions. Designed and manufactured in North America, our machines excel with high-speed cutting, advanced motion control, and customizable options like automatic tool changers, ensuring efficiency and accuracy across a wide range of applications. | F14: https://directory.imts.com/8_0/exhibitor/exhibitor-details.cfm?exhid=1002075
A15: Beijing Worldia Diamond Tools Co.,Ltd. | B15: 431487 | C15: West L3 | D15: Tool Holders & Adapters | E15: Beijing Worldia (est. 2006) specializes in high-precision cutting tools, superhard materials, and CVD diamond functions. Serving the global tool market with MCD/PCD/PCBN and carbide, it also drives industrialization of diamond materials for heat spreaders, optical windows, BDD electrodes, and tweeter domes. | F15: https://directory.imts.com/8_0/exhibitor/exhibitor-details.cfm?exhid=00073225
A16: BIG DAISHOWA | B16: 431610 | C16: West L3 | D16: Collet Chucks, Hydraulic Toolholders, Tool Holders & Adapters, Tool Presetting Equipment | E16: BIG DAISHOWA designs, manufactures and markets high-precision tooling systems and solutions for the automotive, aerospace, medical, agriculture and energy industries. Our portfolio includes CNC tool holders, precision boring tools, cutting tools, tool presetters and workholding solutions. | F16: https://directory.imts.com/8_0/exhibitor/exhibitor-details.cfm?exhid=00002875
A17: Birla Precision Technologies Limited | B17: 432188 | C17: West L3 | D17: Tool Holders & Adapters | E17: Birla Precision Technologies Ltd. provides industrial tooling solutions and was established in 1937 as one of India's first cutting tool manufacturers. Today, we manufacture a wide range of high-precision tools including High-Speed Steel Cutting Tools, Carbide Tools & CNC Tool Holders. | F17: https://directory.imts.com/8_0/exhibitor/exhibitor-details.cfm?exhid=00054317
A18: BISON USA Corp. | B18: 431670 | C18: West L3 | D18: Tool Holders & Adapters | E18: BISON-BIAL, founded in 1948, is the largest manufacturer in Poland of technological tooling for manufacturing and has been a world leader in the machine tool accessory industry for decades. Bison produces a wide range of machine tool accessories used in the aerospace, energy, automotive, medical, defense and subcontract industries. | F18: https://directory.imts.com/8_0/exhibitor/exhibitor-details.cfm?exhid=00070421
A19: C.A.M.S. SRL | B19: 237212 | C19: North L3 | D19: Tool Holders & Adapters | E19: Since 1975 CAMS has been operating as manufacturer of NC Slotting machines and tools for cutting of precise key-ways, splines, taper key-ways etc. U.S. distributor: Broaching Technologies LLC Menomonee Falls, WI 53051, Mr. Mark Meinhardt, ph. 262-820-1200, sales@broachingtech.com | F19: https://directory.imts.com/8_0/exhibitor/exhibitor-details.cfm?exhid=00083402
A20: CAMWorks by HCLSoftware | B20: 133330 | C20: East L3 | D20: Other | E20: CAMWorks and SOLIDWORKS CAM, developed by HCLSoftware, save programming time and increase efficiency for CNC machining with a truly integrated CAD/CAM solution. Design and manufacturing data are stored in a single file – there is no need to maintain separate CAD and CAM files – and when design changes are made, the toolpaths and G-code are updated automatically. CAMWorks and SOLIDWORKS CAM also us | F20: https://directory.imts.com/8_0/exhibitor/exhibitor-details.cfm?exhid=00002096
A21: Canela Corporation | B21: 432292 | C21: West L3 | D21: Tool Holders & Adapters | E21: Focusing on turning, milling, and made-to-order cutting tools, Canela Corporation is dedicated to distributing the Canela Group's finest precision steel and carbide cutting tools available. As part of an engineering-focused company, Canela Corporation has the technical capability to provide each customer with the best tooling solution for their application. | F21: https://directory.imts.com/8_0/exhibitor/exhibitor-details.cfm?exhid=00035366
... A53: Goltenbodt technology GmbH | B53: 432294 | C53: West L3 | D53: Collet Chucks, Tool Holders & Adapters | E53: Depending on requirements, they can be used for multi-spindle automatic lathes, single-spindle automatic lathes, sliding and fixed headstock automatic lathes as well as grinding machines. Innovation, precision and reliability are the supporting pillars of all GWS products and services. | F53: https://directory.imts.com/8_0/exhibitor/exhibitor-details.cfm?exhid=00064548
A54: GRIP | B54: 432299 | C54: West L3 | D54: Collet Chucks, Hydraulic Toolholders, Tool Holders & Adapters | F54: https://directory.imts.com/8_0/exhibitor/exhibitor-details.cfm?exhid=1003909
A55: Haimer USA | B55: 431510 | C55: West L3 | D55: Hydraulic Toolholders, Tool Holders & Adapters | E55: HAIMER is a first class German Tool Holder manufacturer. From the basics of face-mill arbors and ER collet chucks, all the way up to High Precision Collet and Shrink Fit Chucks, HAIMER has the tools necessary to satisfy and exceed your machining center needs. | F55: https://directory.imts.com/8_0/exhibitor/exhibitor-details.cfm?exhid=00049702
A56: Halder, Inc. | B56: 432246 | C56: West L3 | D56: Hydraulic Toolholders | E56: We are a leading manufacturer of inch and metric standard parts. This includes spring plungers, quick release pins, handles, knobs, lifting devices, clamps, and over 13,000+ parts. | F56: https://directory.imts.com/8_0/exhibitor/exhibitor-details.cfm?exhid=00036859
A57: Harbin Pioneer M&E Technical Development Co., Ltd. | B57: 134568 | C57: East L3 | D57: Tool Presetting Equipment | E57: Harbin Pioneer M&E Technical Development Co., Ltd. was founded in 1995. It is a leader manufacturer of CNC machine tool probe products in China, focusing on machine tool in machine testing for more than 30 years, and is committed to improving the manufacturing level of China's mechanical processing industry. | F57: https://directory.imts.com/8_0/exhibitor/exhibitor-details.cfm?exhid=00041554
A58: HEIDENHAIN Corp. (Student Summit) | B58: 211910 | C58: North L1 | D58: Tool Presetting Equipment | E58: Visit the HEIDENHAIN CORPORATION Student Summit booth #211910 for a hands-on look at the future of manufacturing. Experience the new MILLPWRCT CNC control and droPWR digital readout platform, then take on the Precision Arcade to discover how precision, consistency, and focus drive success in both competition and modern machining. | F58: https://directory.imts.com/8_0/exhibitor/exhibitor-details.cfm?exhid=1001666
A59: Hennig, Inc. | B59: 339133 | C59: South L3 | D59: Tool Holders & Adapters | E59: One partner. One Ecosystem. Make Your Shop Flow Hennig helps manufacturers keep their machines running safely, efficiently, and accurately. We're not just a parts vendor, we're a full machine tool ecosystem partner, covering chip and coolant management, machine protection, tool clamping, machining automation, spindle service, and software. From our headquarters in Machesney Park, Illinois, we supp | F59: https://directory.imts.com/8_0/exhibitor/exhibitor-details.cfm?exhid=00001033
A60: High Tech Research, Inc. - MICRONITE | B60: 135723 | C60: East L3 | D60: Other | E60: MICRONITE software transforms the machine shop's process control chain. Advanced analytics and visualization is applied to every step of operation control. Intuitive dashboards provide clear insights into root causes of machining variation and trends. Automated data analysis makes it easy for engineers and managers to spot problems and make decisions. | F60: https://directory.imts.com/8_0/exhibitor/exhibitor-details.cfm?exhid=00002903
A61: Horn USA, Inc. | B61: 431722 | C61: West L3 | D61: Hydraulic Toolholders, Tool Holders & Adapters | E61: We turn technical ideas into precise, reliable machining results. Through advanced cutting materials, engineering, and application-driven solutions, we help manufacturers solve real problems, improve their processes, and move faster — because speed matters more than size. | F61: https://directory.imts.com/8_0/exhibitor/exhibitor-details.cfm?exhid=00006901
A62: Hänel Storage Systems | B62: 431653 | C62: West L3 | D62: Balancing Machines | E62: Hänel offers best-in-class automated vertical storage, with the Rotomat Vertical Carousel and Lean-Lift Vertical Lift Module, which help customers: 1) Reclaim up to 80% of floor space; 2) Boost inventory accuracy to over 99%; 3) Pick more parts in less time; 4) Enhance inventory security; and 5) Improve workplace ergonomics. | F62: https://directory.imts.com/8_0/exhibitor/exhibitor-details.cfm?exhid=00002706
A63: IMC Group | B63: 431522 | C63: West L3 | D63: Collet Chucks, Hydraulic Toolholders, Other, Tool Holders & Adapters | F63: https://directory.imts.com/8_0/exhibitor/exhibitor-details.cfm?exhid=00054002
A64: IMC Group 2 | B64: 431440 | C64: West L3 | D64: Collet Chucks, Hydraulic Toolholders, Tool Holders & Adapters | F64: https://directory.imts.com/8_0/exhibitor/exhibitor-details.cfm?exhid=1001635
A65: Infor | B65: 135822 | C65: East L3 | D65: Other | E65: o Infor is a global leader in business cloud software specialized by industry. We develop complete solutions for our focus industries, including industrial manufacturing, distribution, healthcare, food & beverage, automotive, aerospace & defense, and high-tech. Infor’s mission-critical enterprise applications and services are designed to deliver sustainable operational advantages with security and | F65: https://directory.imts.com/8_0/exhibitor/exhibitor-details.cfm?exhid=00060411
A66: Infranor Inc. | B66: 237361 | C66: North L3 | D66: Tool Holders & Adapters | E66: At Infranor, our primary goal is to improve our customers' machine performance and value. For nearly 60 years, we have been developing leading-edge technology and optimized solutions to meet this goal. Our top-tier components include servos, spindles, gearboxes, rotary tables, tool holders, and more. | F66: https://directory.imts.com/8_0/exhibitor/exhibitor-details.cfm?exhid=1003866
A67: Ingersoll Cutting Tools | B67: 431522 | C67: West L3 | D67: Hydraulic Toolholders, Tool Holders & Adapters | E67: Ingersoll Cutting Tools has been a leader in the design and manufacture of standard and special indexable metal removal tooling for more than 100 years. Our long history of innovation and experience qualifies us to act as your productivity partner and full-line supplier in the challenging arena of metal removal technology. Experience. Quality. Innovation. // Since 1889 | F67: https://directory.imts.com/8_0/exhibitor/exhibitor-details.cfm?exhid=00002545
A68: Intelligent Dispensing Solutions (IDS) | B68: 432281 | C68: West L3 | D68: Other | F68: https://directory.imts.com/8_0/exhibitor/exhibitor-details.cfm?exhid=1004810
A69: Iscar | B69: 431522 | C69: West L3 | D69: Hydraulic Toolholders, Tool Holders & Adapters | E69: Iscar is a global supplier of cutting tools for use with CNC machine tools. Our core competency lies with our non-stop engineering R&D effort to continually improve the productivity of the metal removal process. We provide performance solutions that reduce cycle time, machine tool power consumption, and increase production consistency. | F69: https://directory.imts.com/8_0/exhibitor/exhibitor-details.cfm?exhid=00001129
A70: iSwiss Corporation | B70: 431379 | C70: West L3 | D70: Hydraulic Toolholders, Tool Holders & Adapters | E70: iSwiss Corporation is a supplier of high-quality tool and work holding, as well as cutting tools. iSwiss is also an authorized BIMU cutting tools representative in the United States. iSwiss is expanding its product line by adding Quick Exchange Collets engineered specifically for CNC lathes and quick-grip workholding applications. We created our business around providing customers the best quality | F70: https://directory.imts.com/8_0/exhibitor/exhibitor-details.cfm?exhid=00080381
A71: Jergens, Inc. | B71: 431910 | C71: West L3 | D71: Hydraulic Toolholders | E71: Jergens Inc is a global manufacturing leader of CNC machining custom workholding products. Today, you'll find our vises, clamps & fixturing systems, tooling components, at work in just about every segment of the metalcutting industry on every continent. And our innovative engineered solutions like the patented Ball Lock®️ Mounting System and Fixture-Pro®️ 5-axis workholding have changed the way ma | F71: https://directory.imts.com/8_0/exhibitor/exhibitor-details.cfm?exhid=00001130
A72: Jimmore International Corp. | B72: 431308 | C72: West L3 | D72: Hydraulic Toolholders, Tool Holders & Adapters | E72: Since 1987, Jimmore has supplied patented, Taiwan-made Nine9 tools through distribution channels. Covering Spot Drill, Engraving Tool, Corner Rounding Tool, Centering Tool, NC Helix Drill, Chamfer & Chamfer Tool, Threading Tools and more, these high-performance ranges prove that special in the industry is our standard line, firmly setting the global. | F72: https://directory.imts.com/8_0/exhibitor/exhibitor-details.cfm?exhid=1003477
A73: Jin Kou Enterprise Co., Ltd. | B73: 432428 | C73: West L3 | D73: Hydraulic Toolholders | E73: We are leading manufacturers of Quick Release Pins, Ring Detent Pins, Pull Pins and special screw, as well as an exporter-maker in Taiwan and exported to the world wide for more than several decades, special for U.S.A., Europe, and Asia market. | F73: https://directory.imts.com/8_0/exhibitor/exhibitor-details.cfm?exhid=00070947
A74: JM Performance Products, Inc. | B74: 431961 | C74: West L3 | D74: Hydraulic Toolholders, Tool Holders & Adapters | E74: JM Performance Products, Inc., the Industry Leader in CNC Spindle Optimization, manufactures a complement of products designed to ensure maximum toolholder to spindle contact. JMPP's patented High Torque© retention knobs eliminate toolholder expansion caused by the installation of a standard retention knob in the V-Flange toolholder. High Torque© retention knobs are guaranteed to improve tooling p | F74: https://directory.imts.com/8_0/exhibitor/exhibitor-details.cfm?exhid=00056008
A75: JobPack Scheduling, Machine Monitoring, & DNC Solutions | B75: 133120 | C75: East L3 | D75: Other | E75: JobPack&#174;&#160;scheduling and analytics software has been providing robust production management software solutions for over 20 years&#160;specifically designed to boost the efficiency of metal cutting manufacturing companies in the aerospace, automotive, and job-shop industries. | F75: https://directory.imts.com/8_0/exhibitor/exhibitor-details.cfm?exhid=00046382
A76: Kaiser Manufacturing | B76: 432141 | C76: West L3 | D76: Balancing Machines | E76: Kaiser Manufacturing makes custom, two-color Kaizen Shadow Foam organizers to protect tools and accessories. They are ideal for manufacturing environments focused on Lean strategies, 5S and help with general workspace organization. Also offering 3D scanning and 3D modeling as a service. Check out our compact CNC toolholder storage, Tool Caddy. | F76: https://directory.imts.com/8_0/exhibitor/exhibitor-details.cfm?exhid=00088606
A77: KASTO, Inc. | B77: 236756 | C77: North L3 | D77: Balancing Machines | E77: KASTO is a global market leader in metal sawing machines, storage systems, and automated handling equipment for metal bar stock, sheet metal, and cut-to-size parts. For more than 50 years, KASTO Inc. has supplied the U.S. market with innovative sawing and storage technology engineered in Germany. | F77: https://directory.imts.com/8_0/exhibitor/exhibitor-details.cfm?exhid=00000325
A78: Kato Mfg. Co., Ltd. | B78: 432196 | C78: West L3 | D78: Hydraulic Toolholders, Tool Holders & Adapters | E78: Founded 1918, leading Japan in tap holders; solving TAPPING and DEBURRING issues. We are a Japanese manufacturer serving electronics, automotive, molds, aerospace, and heavy industries. Our tapping and deburring holders improve machining efficiency, stabilize manual deburring quality, and provide reliable solutions for tapping challenges across diverse industrial applications. | F78: https://directory.imts.com/8_0/exhibitor/exhibitor-details.cfm?exhid=1003747
A79: Kennametal Inc. | B79: 431800 | C79: West L3 | D79: Collet Chucks, Hydraulic Toolholders, Tool Holders & Adapters | E79: Our story is one of continuous innovation. It starts in 1938 with our founder, metallurgist Philip M. McKenna, who after years of research created a tungsten-titanium carbide alloy specifically for cutting tools. That single development not only led to a new class of machining tools that cut faster, lasted longer and drove productivity in everything from the automobile to the airplane, but also le | F79: https://directory.imts.com/8_0/exhibitor/exhibitor-details.cfm?exhid=00004272
A80: Koma Precision, Inc. | B80: 338754 | C80: South L3 | D80: Hydraulic Toolholders, Tool Holders & Adapters | E80: Since 1982, Koma Precision, Inc. has supplied the world’s highest quality machine tool accessories to North America. We are the exclusive national distributor and service center for Tsudakoma rotary tables, Alberti angle heads & live tools, Romai angle heads, Inbis swiss tools and our own line of automated part loaders and tool presetters. | F80: https://directory.imts.com/8_0/exhibitor/exhibitor-details.cfm?exhid=00001035
... A126: Scientific Cutting Tools | B126: 432414 | C126: West L3 | D126: Hydraulic Toolholders, Tool Holders & Adapters | E126: Scientific Cutting Tools (SCT) is a family-owned American manufacturer based in southern California. Since 1963, we have designed and ground precision carbide cutting tools that deliver reliable accuracy, predictable tool life, and clean finishes in demanding materials and tight-tolerance work. Our product offering spans thread mills, port tools, single point tools, drills, specialty milling tools | F126: https://directory.imts.com/8_0/exhibitor/exhibitor-details.cfm?exhid=00047429
A127: SEKWANG SELUX CO., LTD | B127: 432398 | C127: West L3 | D127: Collet Chucks, Tool Holders & Adapters | F127: https://directory.imts.com/8_0/exhibitor/exhibitor-details.cfm?exhid=1003916
A128: Shandong Fangzheng Machine Tool Co., Ltd | B128: 431258 | C128: West L3 | D128: Tool Holders & Adapters | E128: We are professional manufacturer specializing in the production of series of collet chucks, NC tool holders, precision vise and other precision machine tool accessories. | F128: https://directory.imts.com/8_0/exhibitor/exhibitor-details.cfm?exhid=1003548
A129: SHANDONG JINJIE MACHINERY CO.,LTD. | B129: 431370 | C129: West L3 | D129: Tool Holders & Adapters | E129: Bright tools is one of the largest tool holder manufacturer in China. Comprehensive range of Collet / Power Milling / Hydraulic / Shrink Fit Holders for high-precision and high-rigidity applications. | F129: https://directory.imts.com/8_0/exhibitor/exhibitor-details.cfm?exhid=00059848
A130: SHANDONG OUNUOWEI NUMERICAL CONTROL TOOL CO.,LTD. | B130: 431264 | C130: West L3 | D130: Collet Chucks, Hydraulic Toolholders, Tool Holders & Adapters | E130: Ounuowei Numerical Control Tool is a national high-tech enterprise specializing in R&D and production of mid-to-high-end CNC cutting tools. Main products: High-precision CNC tool holders,PSC/HSK/BBT/BT/ISO/series,damping tool ,hydraulic chucks,shrink fit chucks ,high-precision collets ER/SK/HC , high-end face milling cutter ,end mills,corn milling cutters, and peripheral products of machining cent | F130: https://directory.imts.com/8_0/exhibitor/exhibitor-details.cfm?exhid=1001568
A131: Shars Tool Company | B131: 134506 | C131: East L3 | D131: Hydraulic Toolholders, Tool Holders & Adapters | E131: Founded in 1978, Shars Tool Company has been serving the industrial community and machine shops in the USA for over 30 years. As a distributor of affordable tooling for CNC and lathe machines, you are sure to find what you are looking for in our expansive catalog. | F131: https://directory.imts.com/8_0/exhibitor/exhibitor-details.cfm?exhid=00005979
A132: SHENZHEN DANFOO TECHNOLOGY CO.,LTD. | B132: 432316 | C132: West L3 | D132: Balancing Machines, Other | E132: SmartBee, founded in 2015, is a pioneer innovator in smart line-side inventory management solutions, providing integrated hardware and software systems for tools, MRO, and industrial high-value materials. Recognized as an industry leader, SmartBee Helix series ranked No.1 globally in sales in both 2024 and 2025. | F132: https://directory.imts.com/8_0/exhibitor/exhibitor-details.cfm?exhid=1001590
A133: Shobha Industries Private Limited | B133: 431859 | C133: West L3 | D133: Hydraulic Toolholders, Tool Holders & Adapters | E133: Shobha Industries is a leading manufacturer and exporter of high quality work holding and cutting tools. We have been exporting professional tools since 1976 to over 40 countries .We follow international standards such as DIN, GS, ANSI and are ISO 9001:2015 certified for Management and Manufacturing . | F133: https://directory.imts.com/8_0/exhibitor/exhibitor-details.cfm?exhid=00005843
A134: Shop Floor Automations | B134: 133240 | C134: East L3 | D134: Other | E134: YOUR MANUFACTURING INTEGRATION PARTNER, ON AND OFF THE FLOOR As a preferred manufacturing integrator, Shop Floor Automations (SFA) is your partner in manufacturing efficiency. SFA specializes in delivering preeminent automation tools, including shop floor direct numerical control (DNC) communications, machine monitoring software leveraging IIoT technology and CNC hardware solutions, together with | F134: https://directory.imts.com/8_0/exhibitor/exhibitor-details.cfm?exhid=00040271
A135: ShopEdge Software Inc. | B135: 133252 | C135: East L3 | D135: Other | E135: ShopEdge offers a comprehensive ERP Software solution for a variety of devices and operating systems for Metal Stamping and repetitive manufacturing environments with a strong shop floor focus. ShopEdge is the leader in providing highly adaptable, industry focused, ERP solutions that streamline manufacturing from raw materials to | F135: https://directory.imts.com/8_0/exhibitor/exhibitor-details.cfm?exhid=00078475
A136: Sky Hook / Syclone Attco Service | B136: 135950 | C136: East L3 | D136: Balancing Machines, Hydraulic Toolholders | E136: Sky Hook manufactures small, portable, ergonomic lifting devices for safe lifting of awkward, hard to reach loads up to 500 lbs. For lifting applications requiring alternative dimensions or features we can quickly and easily modify the Sky Hook design as needed. The Sky Hook meets applicable OSHA and | F136: https://directory.imts.com/8_0/exhibitor/exhibitor-details.cfm?exhid=00053307
A137: Smart Storage Solutions, Vidmar, LISTA, CribMaster | B137: 431485 | C137: West L3 | D137: Balancing Machines | F137: https://directory.imts.com/8_0/exhibitor/exhibitor-details.cfm?exhid=00032666
A138: Soph, Inc. | B138: 432184 | C138: West L3 | D138: Balancing Machines | E138: Soph Inc. is a magnetic clamping and material handling system manufacturer specializing in electro-permanent, permanent and electromagnetic systems. We manufacture magnets for machine tool work-holding, mold and die clamping in Fenton MI. Soph Inc has full service and repair of all major brands of magnets and controls. | F138: https://directory.imts.com/8_0/exhibitor/exhibitor-details.cfm?exhid=00064740
A139: Southwick & Meister Incorporated | B139: 431271 | C139: West L3 | D139: Tool Holders & Adapters | E139: Southwick & Meister, Inc., since 1952, has been manufacturing precision collets, guide bushings and bar-loader collets for Swiss-Type turning centers and conventional lathes in both standard and customer specific bore configurations. | F139: https://directory.imts.com/8_0/exhibitor/exhibitor-details.cfm?exhid=00000752
A140: Speedgrip Chuck Company | B140: 432157 | C140: West L3 | D140: Hydraulic Toolholders | E140: Speedgrip Chuck Company Delivers Premier Engineered Workholding Solutions For Manufacturers. Our products deliver the highest levels of quality and productivity for customers in every industry where metal cutting is a part of the manufacturing process. | F140: https://directory.imts.com/8_0/exhibitor/exhibitor-details.cfm?exhid=00003378
A141: SPINTECH TOOLS | B141: 431692 | C141: West L3 | D141: Collet Chucks, Tool Holders & Adapters | E141: SpinTech Tools provides high precision workholding and clamping solutions for lathes, grinders, milling machines, and gear hobbers. We serve the machining industry across the U.S., Canada, and Mexico with face drivers, live centers, dead centers, drive pins, center points, adapters, reducing sleeves, sliding jaw mandrels, chucks, and steady rests. | F141: https://directory.imts.com/8_0/exhibitor/exhibitor-details.cfm?exhid=00063865
A142: Spokbee Inc | B142: 236046 | C142: North L3 | D142: Other | E142: Spokbee helps manufacturers launch AI-powered 3D product configurators that connect sales, engineering, and ecommerce. Customers can visualize options, validate rules, get pricing, and submit quotes online. Built for complex configurable products, Spokbee turns manual quoting workflows into fast, interactive buying experiences across websites, dealer portals, and sales teams. | F142: https://directory.imts.com/8_0/exhibitor/exhibitor-details.cfm?exhid=1001043
A143: Star Cutter Company | B143: 237013 | C143: North L3 | D143: Tool Holders & Adapters | E143: THE STAR CUTTER FAMILY OF COMPANIES Headquartered in Farmington Hills, MI, and originally founded in 1927, the Star Cutter Company is a global leader in the cutting tool industry with over 700 employees working in 15 manufacturing facilities. Each facility specializes in producing a specific type of product or service: carbide blanks and preforms, solid carbide cutting tools, gundrills, PCD toolin | F143: https://directory.imts.com/8_0/exhibitor/exhibitor-details.cfm?exhid=00000149
A144: Stevens Engineering, Inc. | B144: 432139 | C144: West L3 | D144: Hydraulic Toolholders | E144: Manufacturer of steel & aluminum workholding products for vertical & horizontal machining centers. | F144: https://directory.imts.com/8_0/exhibitor/exhibitor-details.cfm?exhid=00001206
A145: Stor-Loc | B145: 431474 | C145: West L3 | D145: Tool Holders & Adapters | E145: We build heavy duty tool cabinets, workbenches, CNC tool caddy's, press brakes and storage units. | F145: https://directory.imts.com/8_0/exhibitor/exhibitor-details.cfm?exhid=00005858
A146: Stratasys | B146: 338460 | C146: South L3 | D146: Tool Holders & Adapters | E146: Stratasys is leading the global shift to additive manufacturing with innovative 3D printing solutions for industries like aerospace, automotive, consumer products and healthcare. Through smart and connected 3D printers, polymer materials, a software ecosystem, and parts on demand, Stratasys delivers competitive advantages at every stage in the product value chain. | F146: https://directory.imts.com/8_0/exhibitor/exhibitor-details.cfm?exhid=00004698
A147: Suhner USA | B147: 431314 | C147: West L3 | D147: Hydraulic Toolholders, Tool Holders & Adapters | E147: Suhner is a global company providing material removal products and knowledge for grinding, sanding and polishing applications through robotic end effectors and compliance, abrasive hand tools, abrasive consumables, machining equipment for drilling, tapping, milling and transmission products to serve all industries from industrial, commercial, aerospace, medical, pharmaceutical, automotive, & more. | F147: https://directory.imts.com/8_0/exhibitor/exhibitor-details.cfm?exhid=00030317
A148: System 3R | B148: 339458 | C148: South L3 | D148: Hydraulic Toolholders, Tool Holders & Adapters | E148: System 3R is the leading supplier of productivity-enhancing tools and knowledge for the manufacturing industry, delivering complete solutions and services to world-class Electrical Discharge Machining (EDM), Laser texturing, Additive Manufacturing and Milling machines with tooling, automation and software systems backed with unrivaled customer service and support. | F148: https://directory.imts.com/8_0/exhibitor/exhibitor-details.cfm?exhid=00001350
A149: Taiki Industrial Co., Ltd. | B149: 431987 | C149: West L3 | D149: Collet Chucks, Hydraulic Toolholders, Tool Holders & Adapters | E149: TAIKI is the epitome of excellence in Taiwanese Soft Jaws and Accessories of Power Chuck manufacturing. It has set up a Broaching Machine and CNC Machine Center which can broach and drill the best quality castings and get perfect shapes. | F149: https://directory.imts.com/8_0/exhibitor/exhibitor-details.cfm?exhid=00052682
... A151: TDM Systems Inc. | B151: 133125 | C151: East L3 | D151: Balancing Machines, Other | E151: TDM Systems helps manufacturers / CNC plants manage tool data and tool lifecycles for greater efficiency. CRIBWISE provides real-time tooling and inventory management to improve visibility and reduce costs. Toolhive is a cloud-based tool management solution that simplifies tooling processes and connects planning, inventory, and shopfloor operations for greater efficiency. | F151: https://directory.imts.com/8_0/exhibitor/exhibitor-details.cfm?exhid=00047637
A152: Tenpro Advanced Technologies Co., Ltd. | B152: 236834 | C152: North L3 | D152: Balancing Machines | F152: https://directory.imts.com/8_0/exhibitor/exhibitor-details.cfm?exhid=1004667
A153: TOOL HOLDER SHOP INC. | B153: 432097 | C153: West L3 | D153: Collet Chucks, Tool Holders & Adapters | E153: CNC machine tools tool holders distributor | F153: https://directory.imts.com/8_0/exhibitor/exhibitor-details.cfm?exhid=1001613
A154: Torkoal Tools Kft. | B154: 432295 | C154: West L3 | D154: Collet Chucks | F154: https://directory.imts.com/8_0/exhibitor/exhibitor-details.cfm?exhid=1004318
A155: TSENSE TECHNOLOGY CO., LTD. | B155: 236834 | C155: North L3 | D155: Tool Presetting Equipment | E155: T-sense Technology Co., Ltd. is a leading developer and manufacturer of high-precision CNC measurement solutions, mold monitoring tools, and linear motion components. Driven by innovation, we provide high-rigidity, ultra-stable equipment upgrades designed to elevate productivity in CNC machining. | F155: https://directory.imts.com/8_0/exhibitor/exhibitor-details.cfm?exhid=00064566
A156: Tsugami America | B156: 339410 | C156: South L3 | D156: Hydraulic Toolholders | E156: Tsugami America has been the exclusive North American importer of Precision Tsugami machine tools since 1978. A division of Morris Group, Inc. in Windsor, Connecticut, Tsugami America sells new Tsugami machine tools via national distribution channels and direct sales agents. Tsugami America also provides application engineering, service, and customer training. | F156: https://directory.imts.com/8_0/exhibitor/exhibitor-details.cfm?exhid=00063256
A157: TTC North America LLC | B157: 432323 | C157: West L3 | D157: Hydraulic Toolholders, Tool Holders & Adapters | E157: TTC North America provides high quality, competitively priced tools and attachments for Swiss machines. Our priority is to keep our customers satisfied and their machines working efficiently. Our high level of IN STOCK products help us deliver most orders within 48-72 hours. | F157: https://directory.imts.com/8_0/exhibitor/exhibitor-details.cfm?exhid=00089695
A158: Tungaloy-NTK America | B158: 431522 | C158: West L3 | D158: Hydraulic Toolholders, Tool Holders & Adapters | E158: Tungaloy-NTK America delivers innovative metal cutting solutions with extensive turning, milling, and drilling products. Our premium ceramics, Swiss Tooling, and advanced systems ensure high-precision performance across industries. With a wide range of grades, dimensions, and chipbreakers, we provide complete tooling solutions. Together, we secure technological power in the machining world. | F158: https://directory.imts.com/8_0/exhibitor/exhibitor-details.cfm?exhid=00001738
A159: U S Shop Tools | B159: 432122 | C159: West L3 | D159: Tool Holders & Adapters | E159: National distributor of machine shop tools and metalworking supplies | F159: https://directory.imts.com/8_0/exhibitor/exhibitor-details.cfm?exhid=00002631
A160: Union Materials Corporation | B160: 432180 | C160: West L3 | D160: Tool Holders & Adapters | E160: We used to known as SsangYoung material Corporation and now we are Union Material Corporation. Indexable insert is our main forte such as Ceramic, PCD, pCBN, Cermet, and some carbide. We also offer tool holders, cutters and endmills. Come and see us today. | F160: https://directory.imts.com/8_0/exhibitor/exhibitor-details.cfm?exhid=00005353
A161: Vargus USA | B161: 432221 | C161: West L3 | D161: Tool Holders & Adapters | E161: VARGUS is a world leading developer, manufacturer and supplier of high-quality, precision threading, grooving, turning and hand deburring tools. Established in 1960, VARGUS is the cutting tools division of the NEUMO Ehrenberg Group, a multinational organization headquartered in Germany. Since the company's inception, VARGUS | F161: https://directory.imts.com/8_0/exhibitor/exhibitor-details.cfm?exhid=00003410
A162: VERNAL ENGINEERING CO., LTD. | B162: 236834,431660 | C162: North L3, West L3 | D162: Tool Holders & Adapters | E162: VERNAL, provide OEM manufacturing expertise with high-precision, complexity, assembly products. Research and develop precision Tool Holders for CNC SWISS type Turning Center. with more complex semi-assembled mechanisms and fully assembled products | F162: https://directory.imts.com/8_0/exhibitor/exhibitor-details.cfm?exhid=00070163
A163: Versatility Professional Tool Storage, LLC | B163: 432094 | C163: West L3 | D163: Balancing Machines | E163: Made in America, Versatility® Cabinets offer the ultimate value in professional tool storage by combining 50 years of manufacturing experience with innovative engineering. The Versatility Product Line includes specialty cabinets for the storage and organization of press brake and turret punching tools; mechanics’ toolboxes; heavy duty general storage cabinets; and workbenches. Versatility Cabinets | F163: https://directory.imts.com/8_0/exhibitor/exhibitor-details.cfm?exhid=00079454
A164: Vortex Tool Co. Inc. | B164: 431273 | C164: West L3 | D164: Tool Holders & Adapters | E164: For more than 30 years, Vortex Tool Company has built a reputation as an innovator, manufacturing high performance tools in the industries. From its facility in Schofield, Wisconsin, Vortex produces tools with cutting edges in various grades of carbide, high-speed steel and polycrystalline diamond. Vortex also provides custom tool design, | F164: https://directory.imts.com/8_0/exhibitor/exhibitor-details.cfm?exhid=00090270
A165: Weidmuller | B165: 236252 | C165: North L3 | D165: Balancing Machines | E165: For 50 years, Weidmuller USA has led innovation in smart industrial connectivity and automation. From pioneering terminal blocks and remote I/O to launching the u-OS open software ecosystem, we empower Industry 4.0 with IIoT solutions and smart cabinet solutions for the future. Weidmuller builds the connections that drive industry forward. | F165: https://directory.imts.com/8_0/exhibitor/exhibitor-details.cfm?exhid=00052767
A166: WinTool USA Inc. | B166: 133368 | C166: East L3 | D166: Hydraulic Toolholders, Other | E166: WinTool simplifies the workflow of CNC production to improve throughput and reduce cost. Customers benefit from a lean Industry 4.0 solution, as well as the extensive experience and knowledge gained by implementations in many different Production Resources & Tools (PRT) Management projects in leading CNC workshops worldwide. | F166: https://directory.imts.com/8_0/exhibitor/exhibitor-details.cfm?exhid=00053651
... A171: ZOLLER Inc. | B171: 432018 | C171: West L3 | D171: Balancing Machines, Collet Chucks, Hydraulic Toolholders, Other, Tool Holders & Adapters, Tool Presetting Equipment | E171: ZOLLER is the global leader in tool presetting, measuring, inspection, balancing, shrinking, automation and tool management technology. The third-generation, family-owned company has provided state-of-the-art solutions for the complete management of cutting tools for more than 75 years. | F171: https://directory.imts.com/8_0/exhibitor/exhibitor-details.cfm?exhid=00006328

Sheet Asia Cluster (West hall)
A1: Company | B1: Booth # | C1: Hall | D1: Description (directory)
A2: ACCU-CUT Industrial Co., Ltd | B2: 432428 | C2: West L3 | D2: Accu-Cut specializes in threading solutions, micro tools from 0.1 mm diameter, end mills, and custom-engineered cutting tools for hardened materials and difficult-to-machine alloys.
A3: ADVANCED NANO COATING TECHNOLOGY CO.,LTD. | B3: 431292 | C3: West L3 | D3: Advanced Nano Coating Technology Co., Ltd. is the first domestic private enterprise in China that integrates CVD equipment (chemical vapor deposition) design, research and development, manufacturing, sales, after-sales service, spare parts service, and CVD coating processing services.
A4: Beijing Worldia Diamond Tools Co.,Ltd. | B4: 431487 | C4: West L3 | D4: Beijing Worldia (est. 2006) specializes in high-precision cutting tools, superhard materials, and CVD diamond functions. Serving the global tool market with MCD/PCD/PCBN and carbide, it also drives industrialization of diamond materials for heat spreaders, optical windows, BDD electrodes, and tweete
A5: CELETOGETHER MACHINERY(KUNSHAN)CO.,LTD. | B5: 431290 | C5: West L3 | D5: Celetogether founded in China 2008, including MC modular fixtures, zero-point automatic quick-change systems, high-precision base plates & tooling column, multi-station parallel vises, CNC 4-axis and 5-axis rotary tables, providing professional clamping solutions for global machinery industry.
A6: CHAIN HEADWAY CO., LTD. | B6: 431855 | C6: West L3 | D6: Chain Headway, established in 1992 in Taiwan, is dedicated to providing cutting-edge metal cutting solutions designed to enhance customer productivity. As a leading manufacturer of CNC cutting tools and inserts, we leverage our extensive know-how to understand our customers' needs and deliver innova
A7: CHEIL GRINDING WHEEL IND.CO.,LTD | B7: 432289 | C7: West L3 | D7: Since 1955, CHEIL GRINDING WHEEL, has been manufacturing high quality grinding wheel products to meet the wide range of industrial grinding, cutting and finishing applications. In addition to tight quality control standards, more than 150,000 different specifications' item have been manufacturing in
A8: CHN-TOP SCI & TECH CO.,LTD | B8: 431270 | C8: West L3 | D8: Specialized in diamond tools (PCD, PCBN, MD, ND, CVD) industries, PCD/PCBN tools’ grinders, vacuum brazing machines, laser cutting and engraving machines, laser processing center; Pre-machining services (PCD/PCBN laser cutting, tools brazing, chip breaker engraving, lapping and polishing ), Distribu
A9: CMT Co.,Ltd. | B9: 431698 | C9: West L3 | D9: We are a manufacturer of cutting tool parts. We maintain stable and long-term partnerships with major companies such as KORLOY, DINE and TaeguTec as well as many other business partners, as we continue to grow together.
A10: CMTBA - China Machine Tool & Tool Builders’ Association | B10: 432580 | C10: West L3
A11: DALIAN RICHUAN PRECISE MOULD PRODUCTS CO.,LTD | B11: 431393 | C11: West L3 | D11: Our company primarily processes stamping mold components, motor mold components, new energy battery mold components, die-casting mold components, powder metallurgy mold components, and automated custom components, We also have a total of more than 140 processing and testing equipment.
A12: DK Metals | B12: 432461 | C12: West L3 | D12: Metal fabricator specializing in Castings and Machined products. We also produce Forged and Stamped products. A Private enterprise in operations for 18 years. We have 4 factories, with our Main Office in Nanjing, China. We also have a Technical and Sales support office near Detroit, Michigan.
A13: EUNSUNG CO., LTD. | B13: 432393 | C13: West L3 | D13: Eunsung Co., LTD was established in 1992 to manufacture and distribute the wire rods made of non-ferrous metals and special alloys as EDM WIRE, BRASS WIRE, COPPER WIRE etc..
A14: EVERMORE MACHINE CO., LTD. | B14: 431756 | C14: West L3 | D14: Established in 1979 specializing in the manufacture of Keyless Drill Chucks, VDI / BMT turning/milling live holders, and in 2002 producing CNC tool holder, Boring tooling, HSK & PSC holders and other precision accessories. Evermore is a trusted supplier to big names in the machine tool industry arou
A15: Flair Machinery Accessory Co., Ltd. | B15: 432093 | C15: West L3 | D15: Flair factory located in Taichung city of Taiwan. Head company Chang Steel Electronic & Machine Tools Co., Ltd. and Flair Machinery Accessory Co., Ltd. We specialize in development, manufacture and trading of machine components. Our Main products are Hand Wheels, Handles, Pulleys, Coupling, Casting,
A16: Fodbits Precision Technology Co., Ltd. | B16: 432133 | C16: West L3 | D16: FODBITS Company spent 12 years developing the drill chuck that hole-making tools have been waiting 123 years for—one engineered to unleash their full potential. The chuck and the tools work in perfect sync, bringing out the best in each other. It’s the perfect match.**
A17: GSA Technology Co., Ltd. | B17: 431854 | C17: West L3 | D17: GSA is a Taiwanese machine tool accessories manufacturer. Products: CNC rotary table, Tilting rotary table, Roller Gear-Cam rotary table, Horizontal machining center table with pallets, Large size horizontal rotary table for CNC machining center. Hydraulic/Servo drive/Power tooling Turret for CNC La
A18: Guangdong Huasheng Nanotechnology Co., Ltd. | B18: 431386 | C18: West L3 | D18: Guangdong Huasheng Nanotechnology Co., Ltd. specializes in R&D and manufacture of PVD/DLC/HFCVD/ta-C vacuum coating machines, delivering integrated nano coating solutions for cutting tools and components with proprietary core patents.
A19: HANGZHOU ANKA TOOLS CO., LTD. | B19: 431293 | C19: West L3 | D19: HANGZHOU ANKA TOOL CO., LTD. is a leading manufacturer of high-quality metal cutting tools, specializing in annular cutters, rail cutters, HSS step drills, and TCT hole saws. Our strength is built on innovation, premium quality, superior service, and competitive pricing.
A20: HANSONG M&T | B20: 431781 | C20: West L3 | D20: Hansong, founded in 1999, is Korea’s leading manufacturer of carbide end mills and dental burs. Exporting to over 60 countries, Hansong is recognized for its innovation, quality, and successful localization in cutting tool production.
A21: Hon Jan Cutting Tools Co., Ltd. | B21: 431661 | C21: West L3 | D21: HonJan Cutting Tools was founded in 1989 and we connected to the global market with the brand "SHAN GIN TOOLS". Our company has been producing indexable cutting tools for over 37 years. Our product lines contain boring bars, lathe turning tools, threading, grooving, milling, boring tools, cartridges
A22: HONGIK DIAMOND Co., Ltd | B22: 431489 | C22: West L3
A23: Hypermax Machinery Co., Ltd. | B23: 432431 | C23: West L3 | D23: Hypermax Machinery Co., Ltd., with over 40 years of experience in manufacturing grinding machines, has been cultivating expertise in grinding processes and investing in the latest technologies. We are continuously improving our research team’s competitiveness to provide customers with more choices a
A24: Innox Tools (Guangzhou) Co., Ltd | B24: 431272 | C24: West L3 | D24: Innox Tools develops and manufactures innovative HSS and carbide cutting tools. TWISTCUT brand is recognized worldwide for its quality, precision and durability.
A25: Jimmore International Corp. | B25: 431308 | C25: West L3 | D25: Since 1987, Jimmore has supplied patented, Taiwan-made Nine9 tools through distribution channels. Covering Spot Drill, Engraving Tool, Corner Rounding Tool, Centering Tool, NC Helix Drill, Chamfer & Chamfer Tool, Threading Tools and more, these high-performance ranges prove that special in the indus
A26: Jin Kou Enterprise Co., Ltd. | B26: 432428 | C26: West L3 | D26: We are leading manufacturers of Quick Release Pins, Ring Detent Pins, Pull Pins and special screw, as well as an exporter-maker in Taiwan and exported to the world wide for more than several decades, special for U.S.A., Europe, and Asia market.
A27: Kato Mfg. Co., Ltd. | B27: 432196 | C27: West L3 | D27: Founded 1918, leading Japan in tap holders; solving TAPPING and DEBURRING issues. We are a Japanese manufacturer serving electronics, automotive, molds, aerospace, and heavy industries. Our tapping and deburring holders improve machining efficiency, stabilize manual deburring quality, and provide re
A28: KEXIAN PRECISION TOOLS (ZHEJIANG) CO.,LTD. | B28: 431276 | C28: West L3 | D28: Founded in 2014, Kexian is based in Zhejiang and equipped with advanced CNC machines. Boasting core cutting technology as well as ISO and high-enterprise certifications, we develop high-grade precision cutting tools for advanced manufacturing industries.
A29: Kimz Co,. Ltd. | B29: 431593 | C29: West L3 | D29: KIMZ is located in Korea and is a world-leading company in the field of workholding.
A30: KOMMA - Korea Machine Tool Manufacturers Association | B30: 432584 | C30: West L3 | D30: KOMMA has been at the heart of Korea's machine tool industry development, promoting consistent cooperation and collaboration among related stakeholders encompassing the government, research institutes, private sector, etc KOMMA,organizer of SIMTOS,which has grown into a global market platform, inten
A31: KOTRA/KOMMA | B31: 431783 | C31: West L3 | D31: KOMMA has been at the heart of Korea's machine tool industry development, promoting consistent cooperation and collaboration among related stakeholders encompassing the government, research institutes, private sector, etc KOMMA,organizer of SIMTOS,which has grown into a global market platform, inten
A32: Lingbo Group Inc. | B32: 432438 | C32: West L3 | D32: Located in Guangzhou, China, Lingbo Group has been specialized in high precision CNC machining and other metal work since 2001. We now have our US office set in Lisle, IL, focusing on serving all customers in the North America.
A33: LUOYANG REIGN MACHINERY EQUIPMENT CO.,LTD. | B33: 432284 | C33: West L3 | D33: Since 2007, LYREIGN has specialized in CNC tool storage and workshop organization solutions. We provide CNC Tool Cabinets, Tool Carts, Industrial Computer Cabinets, and 5S management systems designed to improve efficiency, productivity, and workspace organization.
A34: NAGAIGIKEN CO., LTD. | B34: 432282 | C34: West L3 | D34: NAGAIGIKEN is a Japanese manufacturer of custom production equipment, automation systems, welding jigs, inspection machines, and material handling solutions. We provide integrated engineering, machining, assembly, electrical control, installation, and commissioning services, supporting manufacturers
... A40: SAMICK PRECISION IND.CO.,LTD | B40: 432253 | C40: West L3 | D40: Linear Ball Bearing(Standard/Open/Flange/Super/Compact), Rail & Shaft, Guide Master(Guide post for heavy ultra precise mould), McGuide(Precision guide for heavy load and high rigidity), Servo Actuator(Electric Actuator that can replace hydraulic or pnuematic cylinder), Picker Actuator(Pneumatic Cyli
A41: SEKWANG SELUX CO., LTD | B41: 432398 | C41: West L3
A42: Shandong Fangzheng Machine Tool Co., Ltd | B42: 431258 | C42: West L3 | D42: We are professional manufacturer specializing in the production of series of collet chucks, NC tool holders, precision vise and other precision machine tool accessories.
A43: SHANDONG JINJIE MACHINERY CO.,LTD. | B43: 431370 | C43: West L3 | D43: Bright tools is one of the largest tool holder manufacturer in China. Comprehensive range of Collet / Power Milling / Hydraulic / Shrink Fit Holders for high-precision and high-rigidity applications.
A44: SHANDONG OUNUOWEI NUMERICAL CONTROL TOOL CO.,LTD. | B44: 431264 | C44: West L3 | D44: Ounuowei Numerical Control Tool is a national high-tech enterprise specializing in R&D and production of mid-to-high-end CNC cutting tools. Main products: High-precision CNC tool holders,PSC/HSK/BBT/BT/ISO/series,damping tool ,hydraulic chucks,shrink fit chucks ,high-precision collets ER/SK/HC , hig
A45: SHANGHAI TOOL WORKS CO.,LTD. | B45: 431274 | C45: West L3 | D45: As a professional tools supplier,Shanghai Tool Works Co.,Ltd. has 70 years history.As a small factory at the beginning,we are now becoming one of the most competitive tool suppliers in China. We provide the professional cutting tools with high efficiency and precision. Our tools are widely accepted
A46: Shanghai Yamada Precision Tools Co., Ltd. | B46: 432231 | C46: West L3 | D46: Shanghai Yamada Precision Tools Co., Ltd., based in Shanghai, is a professional manufacturer of PCD, PCBN and carbide cutting tools since 2001. Its products include inserts, turning tools, reamers, milling tools, drills, boring tools, abrasive tools, etc. It has close cooperation with customers in t
A47: SHENZHEN DANFOO TECHNOLOGY CO.,LTD. | B47: 432316 | C47: West L3 | D47: SmartBee, founded in 2015, is a pioneer innovator in smart line-side inventory management solutions, providing integrated hardware and software systems for tools, MRO, and industrial high-value materials. Recognized as an industry leader, SmartBee Helix series ranked No.1 globally in sales in both 2
A48: SHIN-IL MACHINERY CO., LTD. | B48: 432232 | C48: West L3 | D48: SHIN-IL Machinery Co., Ltd. is a leading Korean manufacturer of high-precision CNC machines and tools, backed by over 50 years of engineering expertise. Our core products include Deep-hole Drilling Machines (Gun Drill), B.T.A. Systems, Portable Boring Machines for shipbuilding, Notching Milling Mach
A49: Summit Super Abrasive Co., Ltd. | B49: 432326 | C49: West L3 | D49: Summit Super Abrasive leads in advanced abrasive materials, delivering top-quality and innovative products for you.
A50: SunUs Tech | B50: 432436 | C50: West L3 | D50: Over 60 years of expertise and experience, SunUs Tech is a Taiwanese brand that dedicates itself to making planetary gear reducers for all industries. Founded in 2000, SunUs has been certified with ISO:9001 2015 and won Taiwan Excellence Award in 2016.
A51: Superior Intelligent Manufacturing (Shenzhen) Limited | B51: 431383 | C51: West L3 | D51: Superior was established in 2006, the plant area covers 30,000 square meters, has more than 420 employees. It is an ISO 90001:2015 and ISO/IEC 27001:2013 certified high-tech enterprises with comprehensive productive capabilities, including precision CNC machining, 3D printing, vacuum casting, inject
A52: Taiki Industrial Co., Ltd. | B52: 431987 | C52: West L3 | D52: TAIKI is the epitome of excellence in Taiwanese Soft Jaws and Accessories of Power Chuck manufacturing. It has set up a Broaching Machine and CNC Machine Center which can broach and drill the best quality castings and get perfect shapes.
A53: TAMI - Taiwan Association of Machinery Industry | B53: 432575 | C53: West L3 | D53: TAMI is the most historical and leading manufacturers’ association of machinery and machine tools in Taiwan, and treasures all the opportunities in offering the best support to its members with enthusiasm. The Machine Tools sector is the leading area of Taiwan’s machinery industry.
... A68: ZONG YIH RUBBER INDUSTRIAL CO., LTD. | B68: 431766 | C68: West L3 | D68: Zong Yih Rubber Industrial Co., Ltd., established in Taiwan in 1978, specializes in customized rubber parts, rubber-to-metal bonding, seals, gaskets, bushings, and anti-vibration products. With ISO 9001 and IATF 16949 certifications, Zong Yih provides reliable OEM/ODM manufacturing, supported by 64

Sheet All Exhibitors (1752)
A1: Company | B1: Booth # | C1: Hall | D1: Description
A2: 1factory | B2: 134350 | C2: East L3 | D2: 1factory provides easy-to-use yet powerful Manufacturing and Supply Chain Quality Control software. With 1factory, manufacturers can speed-up quality control tasks and ensure the highest product quality.
A3: 3D MicroPrint GmbH | B3: 338278 | C3: South L3 | D3: Small in size, but big in detail! 3D MicroPrint GmbH manufactures high-precision micro metal components using Micro Laser Sintering technology. We offer a comprehensive service from product design and prototype development through to series productio
A4: 3DChimera | B4: 237633 | C4: North L3 | D4: 3DChimera helps manufacturers solve production bottlenecks with 3D scanning, CAD, additive manufacturing, and post-processing systems. We provide equipment, engineering services, training, and support that turn physical parts into digital data, valid
A5: 3nine USA | B5: 432443 | C5: West L3 | D5: 3nine is the world leader in “disc stack” separation for eliminating oil mist produced by CNC machines. Our technology provides for a cleaner and healthier shop environment.
A6: 4D Technology Corporation, an Onto Innovation subsidiary | B6: 134480 | C6: East L3 | D6: 4D Technology, a subsidiary of Onto Innovation, designs and manufactures optical surface gauges, surface roughness profilers and other metrology for accurate 3D, non-contact measurement of precision surfaces. 4D products use patented, state-of-the-ar
A7: 4D1 | B7: 237617 | C7: North L3 | D7: 4D1 delivers millimeter-accurate, drift-free 6DoF positioning without cameras or SLAM. We elevate manufacturing with high fidelity motion intelligence by enforcing rigorous quality control, instantly upskilling human operators with real-time digital
A8: 5th Axis Inc. | B8: 431452 | C8: West L3 | D8: Regarded as one of the world’s most innovative manufacturers, 5th Axis offers a full range of workholding solutions. 5th Axis’s product line includes vises, fixtures, dovetail cutters and the ever-popular Rock Lock quick-change system that provides m
A9: 80/20 LLC | B9: 236419 | C9: North L3 | D9: 80/20 delivers a modular infrastructure platform that replaces welded fabrication with reconfigurable aluminum framing and steel pipe systems. Build machine frames, workstations, and automation structures faster, integrate with existing environments,
A10: A&W TOOL, INC. | B10: 431768 | C10: West L3 | D10: Founded in 1989, A&W Tool Inc. in Ringwood, IL, exists to solve your toughest production challenges. We deliver custom precision CNC manufacturing, resharpening, and tool modifications. Built on exact accuracy and reliable turnarounds, we are absolut
A11: A'S PRECISION MACHINING LTD | B11: 432286 | C11: West L3
A12: AB Tools Inc. | B12: 432264 | C12: West L3 | D12: USA made since 1977, Special Cutting Tools, Home of the Shear Hog® & Accu-hold, Indexable Dovetails, O-Ring grooving tools, Keyseat cutters, Firearms tooling in stock & Specials to your specs in 5-6 workdays.
A13: Abbott Workholding | B13: 339347 | C13: South L3
A14: ABIMAQ - The Brazilian Association of the Machinery & Equipment Industry | B14: 432590 | C14: West L3 | D14: The Brazilian Machinery Builders' Association (ABIMAQ) was founded in 1975 with the goal of acting for the strengthening of the domestic industry by mobilizing the sector, performing actions with the political and economic spheres, stimulating intern
A15: ABRO Balancing Machines Inc. | B15: 134013 | C15: East L3 | D15: Manufacturer of balancing machines for the automotive, power, aerospace and other industries. high speed balancers for turbines and generators. Automatic balancers. fibre laser cutting and welding machines. turret punch press and press brake. made in
A16: ABS Import Tools Inc. | B16: 134618,432083 | C16: East L3, West L3 | D16: Henry Xu founded ABS Import Tools in 1992 to provide high-quality tools and industrial supplies at competitive prices. With a 98% fill rate, the company ensures swift shipping and reliable service. ABS Import Tools now offers products from Dasqua and
A17: Absolent & Diversitech | Part of Absolent Air Care Group | B17: 237542 | C17: North L3 | D17: Absolent and Diversitech (Part of ACG) deliver high-performance air care solutions for demanding industrial applications, including oil mist, oil smoke, fumes and hazardous combustible dust.
A18: Abtex LLC | B18: 237536 | C18: North L3 | D18: Abtex has been designing and manufacturing application-specific abrasive filament deburring brushes and machinery since 1980.
A19: ACCF International Inc - SLOKY USA | B19: 431850 | C19: West L3 | D19: Sloky USA specializes in patented preset torque screwdrivers and adapters for all industries. Their color-coded, interchangeable tools ensure screws are accurately tightened to manufacturer-defined specifications, preventing part damage and guarantee
A20: Accretech SBS Inc. | B20: 237540 | C20: North L3
A21: ACCU-CUT Industrial Co., Ltd | B21: 432428 | C21: West L3 | D21: Accu-Cut specializes in threading solutions, micro tools from 0.1 mm diameter, end mills, and custom-engineered cutting tools for hardened materials and difficult-to-machine alloys.
A22: Accurate Die Design Software, Inc. | B22: 135600 | C22: East L3 | D22: Accurate Die Design Software, Inc. is a provider and expert in software, representing two products: LogoPress, a software for die design, flattening, and forming simulation within SOLIDWORKS, and Stampack, a standalone forming simulation software tha
A23: Accurex Measurement, Inc. | B23: 134650 | C23: East L3 | D23: Accurex Measurement provides high-precision 3D Dimensional Measurement and Testing systems. Special applications include Bent Tube Measurement, Gap &#38; Flush measurement, and deformation analysis. Automated Accurex Lynx Vision systems are used to c
A24: Accustrip ApS | B24: 338999 | C24: South L3
A25: Accutek | B25: 431591 | C25: West L3 | D25: Accutek® is a premier manufacturer of tool holding and work holding solutions. Given the constant evolution of tooling and machining technology plus the ever-increasing needs of our customers for greater accuracy and efficiency, Accutek is committed
A26: Acena Consulting, LLC | B26: 432267 | C26: West L3 | D26: Maximize the return on your innovation. Acena Consulting helps manufacturers secure R&D tax credits and cost segregation benefits with defensible documentation that withstands IRS scrutiny. Visit Booth 432267 to see how your company can increase cash
A27: Acer/Springwood Industrial, Inc. | B27: 339358 | C27: South L3 | D27: Wholesale of metal cutting machinery.
A28: Achieve Technologies Inc | B28: 432256 | C28: West L3 | D28: Achieve Technologies delivers advanced CNC turrets, live tooling, CAPTO/PSC systems, and our patented Machine Tool Robot for high‑precision robotic milling and mill‑turn lathes. Our engineering experts provide turret and application engineering, rebu
A29: Acme Manufacturing | B29: 237030 | C29: North L3 | D29: As a globally recognized machine tool builder and robotic systems integrator, Acme Manufacturing offers turnkey solutions for material removal. Acme Manufacturing specializes in grinding, polishing, buffing, deburring, and cut-off applications with o
A30: ACU-RITE SOLUTIONS | B30: 339440 | C30: South L3 | D30: Acu-Rite Solutions provides CNC controls, digital readout (DRO) systems, CNC retrofit systems, linear encoders, precision measurement, and machine tool controls for milling, turning, and grinding. Our intuitive solutions improve machining accuracy, p
A31: Acumatica | B31: 133112 | C31: East L3 | D31: Acumatica delivers a robust business management solution for manufacturers backed by a vibrant community of partners, customers, and creators invested in helping growing manufacturers thrive in today’s digital economy. Stop by booth #133112 or visit
A32: Acumatica Powered by Algorithm | B32: 135743 | C32: East L3 | D32: 98% first-time go-live success. Industry-leading NPS. Gold-Certified Acumatica experts: come talk to Algorithm about your toughest ERP challenges: data conversion, complex manufacturing, and replacing legacy systems without disruption.
A33: ADAXIS USA Inc. | B33: 338180 | C33: South L3 | D33: ADAXIS develops AdaOne, a software for robotic hybrid manufacturing. It enables users to design, program, simulate, and control additive, subtractive, and inspection processes on industrial robots, cartesian machines, and hybrid cells. Compatible wit
A34: Adcole LLC | B34: 134376 | C34: East L3 | D34: Adcole is a global leader in precision shaft metrology, delivering Trusted Accuracy through advanced automated gaging systems, software, and services for the high precision measurement of cylindrical and eccentric components. Headquartered in Marlbor
A35: ADEK Industrial Computers | B35: 134474 | C35: East L3 | D35: ADEK Industrial Computers is a leading computer manufacturer. We design and build custom computer systems based on exact customer specifications and requirements. We offer a wide variety of industrial computers and commercial grade systems including
A36: Adelbert Haas LLC | B36: 237505 | C36: North L3 | D36: Haas Multigrind ® CB, Multigrind ® CA, and Multigrind ® CU grinding centers can be found in state-of-the-art manufacturing facilities worldwide. Industries include: medical engineering, precision tool manufacturing, gear manufacturing, the aerospace
A37: ADF Systems, Ltd. | B37: 135250 | C37: East L3 | D37: ADF Systems, Ltd is a manufacturer of Parts Washers, Pressure Washers, Evaporators, Downdraft Tables, and other related equipment and Detergents. ADF will have a Conveyor Washer, Top Load Washer, High Pressure Glove Box Washer, and other equipment av
A38: ADICO | B38: 431696 | C38: West L3
A39: Aditya Engimach Private Limited | B39: 432452 | C39: West L3 | D39: We are the close die forged, Rolled Rings, Casting, Precision engineering components manufacturer & exporting company from India.
A40: AdValue Technology, LLC | B40: 237508 | C40: North L3 | D40: AdValue Technology is a leading supplier of high-quality materials for advanced material research and production. We carry diamond micron/nano powders and diamond slurries. We also provide a variety of other materials such as alumina, quartz, sapphir
A41: Advanced Machine & Engineering | B41: 339133 | C41: South L3 | D41: About Advanced Machine & Engineering (AME) Founded in 1966, Advanced Machine & Engineering (AME) is a leading manufacturer and distributor of precision machine tool components and metal-cutting solutions — including AMROK CNC tombstones, fixture plat
A42: Advanced Manufacturing Technical Education Collaborative (AMTEC) | B42: 211844 | C42: North L1 | D42: The Advanced Manufacturing Technical Education Collaborative (AMTEC) is a national network of educational and industry partners committed to preparing highly skilled industrial maintenance and mechatronic technicians.
A43: ADVANCED NANO COATING TECHNOLOGY CO.,LTD. | B43: 431292 | C43: West L3 | D43: Advanced Nano Coating Technology Co., Ltd. is the first domestic private enterprise in China that integrates CVD equipment (chemical vapor deposition) design, research and development, manufacturing, sales, after-sales service, spare parts service, a
A44: Advanced Superabrasives, Inc. | B44: 237150 | C44: North L3 | D44: ASI supplies a broad line of high performance Superabrasive products to a range of industries. More than just making and selling products, we are proud of our reputation for developing successful engineered grinding solutions for customers no matter
A45: Advantive | B45: 135704 | C45: East L3 | D45: Product quality can make or break your manufacturing company’s success. Advantive provides reliable and scalable Quality Management Systems (QMS) built for modern manufacturers of all industries and sizes. Our QMS solutions provide platforms to help
A46: Advent Design | B46: 338598 | C46: South L3 | D46: Established by MIT alumni in 1984, Advent Design Corporation stands out as an innovative engineering company, enhancing the competitiveness of U.S. manufacturers within the global marketplace. Operating from the Mid-Atlantic, our company extends its
A47: Aeroex Technologies Inc. | B47: 135684 | C47: East L3 | D47: Aeroex Technologies designs and manufactures industrial air filtration systems for metalworking, including the Mist-Fit, MAV, and Blowbox lines. Our mist, smoke, and fume collectors keep CNC machines running cleaner and shops safer. Built in North Am
A48: AEROGO, INC. | B48: 135448 | C48: East L3 | D48: AeroGo manufactures innovative load moving solutions utilizing air caster technology to move heavy, awkward, or delicate loads. Companies large and small have partnered with us since 1967, benefiting from our skilled engineering team, experienced pro
A49: AESUB by Scanningspray | B49: 134566 | C49: East L3 | D49: At AESUB we specialize in the development and manufacture of top-quality scanning sprays and consumables for the 3D scanning industry, offering innovative solutions for every potential challenge. With an in-depth knowledge of 3D scanning the AESUB pr
A50: AFC Cable Systems / Atkore International | B50: 135886 | C50: East L3 | D50: Atkore's Flexicon products include flexible metallic and nonmetallic conduit and fittings manufactured and tested to meet and exceed the highest International Industry standards. We have a range of nonmetallic material types: Polyamide (PA6, PA12, PA
... A56: AIDA Engineering Co.,ltd. Okayama, JAPAN | B56: 135961 | C56: East L3 | D56: With over 50 years of history, AIDA Engineering specializes in cold roll forming machines, forming rolls, and shredder blades. We handle the entire process in-house, from initial design to final manufacturing and advanced heat treatment. To guarantee
A57: Aidex Educational Systems | B57: 211200 | C57: North L1
A58: Ailoys GmbH | B58: 237629 | C58: North L3 | D58: Ailoys makes machines smarter. Our acoustic emission sensors and edge AI retrofit onto existing lines, detecting tool wear, cracks, and forming defects in real time. Fewer scrapped parts, less unplanned downtime, fewer surprises in your cost per unit
A59: AIMS Metrology | B59: 134242 | C59: East L3 | D59: AIMS designs and builds CMMs integrated with 5-axis measurement technology for accurate, flexible three-dimensional inspection of in-process and post-process parts in the lab, on the shop floor, or in an automated cell. AIMS offers turnkey solutions
A60: Air Gaging LLC | B60: 134548 | C60: East L3 | D60: We sell and service air gaging including air rings, air probes, multi-circuited gages, air snaps, master setting rings, master setting discs, lvdt probes, air electronic column readouts, gages for rifle barrels, tapers, medical devices, and many othe
A61: Air Quality Engineering, Inc. | B61: 135220 | C61: East L3 | D61: Our mission is to provide clean air solutions that protect people and environments. We fulfill this mission by designing and manufacturing electronic and media based air filtration solutions for machining and manufacturing processes.
A62: Air Turbine Tools | B62: 431645 | C62: West L3 | D62: With power up to 1.4 hp Air Turbine Tools, Motors and Spindles® stay at rated 25,000 to 90,000 RPM in cut. These unique powerful direct drives operate with no heat, no duty cycle and no maintenance with ultra low vibration. Just connect 90 PSI and se
A63: Airflow Systems, Inc. | B63: 237154,432257 | C63: North L3, West L3 | D63: Airflow Systems, Inc., based in Dallas, TX, manufactures 100% American-made air filtration and source capture systems. Since 1985, they’ve provided dust, mist, fume, and exhaust removal solutions engineered for safety, compliance, and efficiency. The
A64: Aixway3D Co., Ltd | B64: 134671 | C64: East L3 | D64: Aixway3D is a company spin-out from the Fraunhofer Institute for Laser Technology (Fraunhofer ILT) in Germany. the company achieves a typical printing accuracy of 2–10 micrometers, a typical surface roughness Ra value of 0.8 micrometers, and enables
A65: AJAX Factory | B65: 339274 | C65: South L3 | D65: We are a traditional Czech manufacturer of professional hand tools – files and rasps for more than 100 years. Today, we offer our customers hundreds of different types of standard and special tools with file, rasp and milled teeth. Since 2004 we are
A66: Ajax TOCCO Magnethermic | B66: 135324 | C66: East L3 | D66: Ajax TOCCO designs and manufactures advanced induction heating systems for industrial applications, including brazing, soldering, annealing, hardening, shrink-fitting, curing, coating, and bonding. Custom solutions designed to deliver precision, reli
A67: Ajile Light Industries | B67: 134625 | C67: East L3
A68: Alconox Inc. | B68: 135788 | C68: East L3 | D68: Alconox Inc. has been manufacturing detergents for critical cleaning applications for over 75 years and is dedicated to being a leader in critical cleaning detergents. We manufacture quality detergents made solely in the United States and provide tec
A69: ALD Vacuum Technologies GmbH | B69: 135470 | C69: East L3 | D69: ALD Vacuum Technologies designs, engineers, and produces advanced vacuum metallurgy, heat treatment and additive manufacturing furnace systems involving many different technologies. Close cooperation with well-known manufacturers and OEMs have streng
A70: Aletiq | B70: 236488 | C70: North L3 | D70: Aletiq is the AI-native PLM built for industrial manufacturers. It centralizes all technical data — drawings, BOMs, specs, design versions, documents — into a single source of truth. Aletiq is intuitive, deploys fast, integrates with your existing CA
A71: ALFING CORPORATION | B71: 135575 | C71: East L3 | D71: From our office in Plymouth, Michigan we provide our North American customers with complete product support, including sales, service, spare parts, project management, simultaneous engineering and system integration. Our goals are about building long
A72: Aligned Vision | B72: 134036 | C72: East L3 | D72: Aligned Vision specializes in smart, automated solutions that accelerate quality manufacturing. We feature AI-driven LASERVISION large-field automatic inspection with laser feedback; LASERGUIDE CAD-directed 3D industrial laser projection; and BUILDGU
A73: Alliance Manufacturing, Inc. | B73: 135452 | C73: East L3 | D73: Alliance Manufacturing, Inc. brings industry-leading aqueous parts washers, vacuum degreasers, and custom cleaning systems to IMTS 2026. See innovative water-based industrial parts cleaning solutions engineered for performance, sustainability, and ea
A74: Alliance Specialties and Laser Sales | B74: 135134 | C74: East L3 | D74: Our goal is to make a difference for our customers through Gratitude, Relationships, Integrity and Tenacity. We do this by providing unmatched quality service. Featuring: polishing, laser welding, engraving, mold maintenance, and hot runner manifold
A75: Allied Machine & Engineering | B75: 431436 | C75: West L3 | D75: Allied Machine & Engineering Corp is a leading manufacturer of holemaking and finishing tooling systems. Allied devotes its advanced engineering and manufacturing capabilities to create the widest selection of value-added tooling available to metal-c
A76: Allied Powers LLC | B76: 236865 | C76: North L3
A77: Allways Precision, LLC | B77: 236723 | C77: North L3 | D77: Allways Precision is your #1 source for Re-manufactured Cincinnati Centerless Grinders. Allways Precision has the largest volume of machines and original Cincinnati components in stock. Complete turnkey packages and full CNC upgrades are available. P
A78: ALMCO | B78: 338009 | C78: South L3 | D78: Proudly made in the USA, ALMCO has been in business for over 75 years manufacturing quality industrial parts washers, industrial deburring, polishing, and tumbling equipment. In addition to a robust line of standard products, ALMCO also designs and m
A79: Aloris Tool Technology Co., Inc. | B79: 431972 | C79: West L3
A80: Alpha Laser-US | B80: 135524 | C80: East L3 | D80: Alpha Laser is dedicated to advancing laser technology across all manufacturing sectors. We offer the best systems on the market, backed by a team of experts to assist our customers. Need laser welding done efficiently? An ALPHA will tackle your toug
A81: Alwa SmartPINS USA Inc. | B81: 135470 | C81: East L3 | D81: ALWA smartPINS specializes in manufacturing modular wokrpiece carrier systems made from high-quality stainless steel and injection-molded plastic pins. Workpiece carriers can be integrated into various stages of production, including cleaning, automa
A82: ALZMETALL Machine Tools USA Inc. | B82: 339166 | C82: South L3 | D82: ALZMETALL Machine Tools is a renowned German based manufacturer and marketer of Machine-Tools serving global markets for more than 81 years. With it´s technologies for drilling, milling, turning and grinding applications ALZMETALL has proven the lead
A83: AM Solutions: A Brand of the Rosler Group | B83: 338280 | C83: South L3 | D83: Rösler Metal Finishing is a global leader in Surface Finishing for all industries. (Mass Finishing equipment, Shot Blasting equipment, Additive Manufacturing equipment, Media and Compounds) We serve North American customers from our 300,000 sq. ft. m
A84: Amada Machinery America | B84: 237200 | C84: North L3 | D84: With more than 75 years of industry experience, Amada Machinery America is committed to helping our customers deliver dependable service and top-quality work with exceptional grinding and sawing solutions.
A85: Amazon Web Services | B85: 236217 | C85: North L3 | D85: Amazon Web Services (AWS) helps manufacturers innovate with cloud, data, and AI. From industrial AI, robotics, and smart factories to engineering, supply chains, and connected products, AWS empowers organizations to modernize operations, improve prod
A86: Ambrell Induction Heating Solutions | B86: 135240 | C86: East L3 | D86: Ambrell, an InTest Company, is a leading manufacturer of induction heating systems. With power supplies ranging from 1 kW to 1,000 kW, there is a system that's perfect for your application. With free application testing from THE LAB, Ambrell will rec
A87: AMDM - Mexican Association of Machine Tool Distributors | B87: 432579 | C87: West L3 | D87: The Mexican Association of Machinery Distributors, A.C. was founded on October 29, 1943. We gather distributors and manufacturers of machine-tools and manufacturing technology , with the purpose of having institutional representation at a national an
A88: AMDT | B88: 236628 | C88: North L3 | D88: AMDT is the global leader in production resilience and OT security software for industrial automation. The company has over 40 years of experience keeping manufacturers running. Our mission is Production Resilience Delivered. That means helping manuf
A89: American Hofmann Corporation | B89: 134680 | C89: East L3 | D89: American Hofmann Corporation offers globally unique products for balancing technology, vibration analysis and highspeed testing. AHC manufactures a complete line of balancing systems (ranging from parts weighing less than one ounce to 75 tons), tooli
A90: AMERICAN INDUSTRIES GROUP | B90: 432344 | C90: West L3 | D90: We leverage local expertise to efficiently manage your operations in a market with unique cultural, legal, and language requirements. By handling Human Resources, Accounting, Tax Compliance, Customs, and Duties, we simplify complexity and reduce admi
A91: American Precision Museum | B91: 211302 | C91: North L1 | D91: Interchangeable parts changed manufacturing forever — and it started here. The American Precision Museum houses the machine tools and metrology instruments from the Robbins & Lawrence Armory, an 1846 building where the American System of Manufacturin
A92: American Technical Publishers | B92: 211108 | C92: North L1 | D92: Career & Technical Training Materials
A93: American Welding Society | B93: 211175 | C93: North L1
A94: AMFG | B94: 135700 | C94: East L3 | D94: We have built the market leading quoting, order intake and production software for high-mix, low volume manufacturing. Our technology is now utilised by 300+ machine shops across 39 countries and 10 time zones, enabling our customers to quote quicker
A95: Amistad Industrial Developers | B95: 432390 | C95: West L3 | D95: Amistad Industrial Developers is a leading Mexican real estate developer with over 45 years of experience and more than 20 million square feet developed nationwide. We specialize in comprehensive industrial real estate solutions across Mexico, offeri
A96: AML | B96: 431765 | C96: West L3 | D96: AML is an innovative, customer-driven manufacturer of AMLUBE metalforming lubricants, metalworking fluids, and protective coatings. We focus on environmentally responsible solutions that support performance, efficiency, and long-term reliability acro
A97: AML3D | B97: 338284 | C97: South L3 | D97: AML3D is the OeM of ARCEMY®. Available in three configurations, ARCEMY® is an industrial metal 3D printer using Wire Additive Manufacturing (WAM®) technology with proprietary software to produce large-scale and exotic material parts. ARCEMY® promotes
A98: Amprius Technologies | B98: 236182 | C98: North L3 | D98: Amprius' silicon anode cells deliver up to 450 Wh/kg and 1,150 Wh/L—among the highest energy densities commercially available today. Built for high energy, high power, and balanced performance, our batteries enable mission-critical advancements acros
A99: AMSOIL Industrial | B99: 431654 | C99: West L3 | D99: AMSOIL has more than five decades of proven performance engineering specialized lubricants designed to solve problems, improve productivity and maximize equipment life. Our Certified Lubrication Specialists leverage their industry and lubricant exper
A100: AMT Emerging Technology Center | B100: 236700 | C100: North L3 | D100: Watch an automated manufacturing cell produce drones live, then see them fly. Stand beside Aires Tide, an 11-foot-tall AI-designed flight-test vehicle. Discover the digital backbone of smart manufacturing with MTConnect. The ETC highlights how public
A101: AMTECH TECHNOCAST PVT. LTD. | B101: 135587 | C101: East L3 | D101: We are leading manufacturing company Approved ISO, PED, AD-WO from India Capability: -Investment Casting: 25 grams. to 100 Kg/pc. All Steel / Supper Alloys Material -Sand Casting: 1 Kg. to 11 Ton / pc. All Cast Iron and SG Iron Grade -Machined Parts:
A102: AMTIL - Australian Manufacturing Technology Institute Limited | B102: 432589 | C102: West L3 | D102: AMTIL is Australia's peak industry body representing manufacturers and technology suppliers across the advanced manufacturing sector. We connect and support businesses through advocacy, industry events, education, networking and market intelligence,
A103: ANAJ Czech, a.s. | B103: 431785 | C103: West L3 | D103: ANAJ Czech, a.s. (Ltd.) is currently one of the leading Czech companies focusing on manufacturing and sharpening of special tools for cutting operations in mechanical engineering.
A104: ANCA CNC Machines | B104: 237406 | C104: North L3 | D104: ANCA is a world leader in the design and manufacture of CNC tool grinding machines, laser markers, automation solutions, motion controls, and sheet metal components. As an advanced manufacturer with diverse capabilities, ANCA provides engineering and
A105: Andustry | B105: 237652 | C105: North L3 | D105: Andustry is an AI-native sourcing agency for industrial equipment.
...

Sheet Sources
A1: Item | B1: Source
A2: Booth numbers / halls / descriptions | B2: https://directory.imts.com/8_0/ (search API pull, 2026-09-12, 1,752 exhibitors)
A3: Show hours, registration, rules | B3: https://www.imts.com/show/faqs.cfm ; https://www.imts.com/exhibitor/pdf/IMTS2026CompleteRulesRegs_V2.pdf
A4: Floor plan / sector locations | B4: https://www.imts.com/read/article-details/Technology-Evolutions-Drive-IMTS-2026-Floor-Plan-Movement/2100/type/Press-Release/5
A5: Conferences & receptions | B5: https://www.imts.com/show/education/conferences.cfm ; https://www.gaccmidwest.org/us/events/german-night-reception-imts-2026-powered-by-wintrust-bank ; https://ntma.org/event/imts-2026/ ; https://www.imts.com/show/education/Elevate.cfm ; https://www.imts.com/show/M4M.cfm
A6: Ellison / DN reception | B6: https://www.ellisontechnologies.com/imts2026
A7: Zoller IMTS 2026 | B7: https://www.newequipment.com/events/imts/news/55396018/zoller-zoller-to-debut-micro-tool-inspection-and-automation-systems-at-imts-2026
A8: Okuma IMTS 2026 | B8: https://www.prnewswire.com/news-releases/okuma-america-corporation-to-exhibit-at-imts-2026-with-comprehensive-lineup-302834361.html
A9: Mazak IMTS 2026 | B9: https://www.mazak.com/us-en/news-media/news/Mazak-Meets-Accelerating-Production-Demands-With-Advanced-Technology-At-IMTS-2026/
A10: Kennametal IMTS 2026 | B10: https://www.prnewswire.com/news-releases/kennametal-unveils-next-level-shop-experience-for-imts-2026-302829082.html
A11: Omega TMM IMTS 2026 | B11: https://omegatmm.com/imts2026/
A12: Fastems IMTS 2026 | B12: https://www.fastems.com/events/imts-2026/
... A19: DMG MORI Chicago Innovation Days | B19: https://event.dmgmori.com/sv/events/idays-chicago-2026-sept
